Workbook
Name SegmentaciónDeDatos_estado_crm: #N/A
Name SegmentaciónDeDatos_estado_crm1: #N/A
Name SegmentaciónDeDatos_estado_crm2: #N/A
Name SegmentaciónDeDatos_FAMILIA: #N/A
Name SegmentaciónDeDatos_FAMILIA1: #N/A
Name SegmentaciónDeDatos_FAMILIA2: #N/A
Name SegmentaciónDeDatos_LINEA: #N/A
Name SegmentaciónDeDatos_LINEA1: #N/A
Name SegmentaciónDeDatos_LINEA2: #N/A
Name SegmentaciónDeDatos_Mes_Entrega: #N/A
Name SegmentaciónDeDatos_Mes_Entrega1: #N/A
Name SegmentaciónDeDatos_Mes_Entrega2: #N/A
Name SegmentaciónDeDatos_oportunidad: #N/A
Name SegmentaciónDeDatos_oportunidad1: #N/A
Name SegmentaciónDeDatos_regional: #N/A

Sheet baseDatos
A1: pedido | B1: cliente | C1: tipo_producto | D1: oportunidad | E1: razon_anulacion | F1: f_cotizacion | G1: f_pedido | H1: f_comercial | I1: f_diseno | J1: f_produccion | K1: f_despachos | L1: f_instalacion | M1: fe_comercial | N1: fe_diseno | O1: fe_produccion | P1: fe_despachos | Q1: fe_instalacion | R1: estado | S1: regional | T1: id_producto | U1: producto | V1: color | W1: color_estructura | X1: cantidad | Y1: largo | Z1: alto | AA1: proyeccion | AB1: valor_total | AC1: estado_crm | AD1: FAMILIA | AE1: LINEA | AF1: Mes Entrega
A2: 13209 | B2: ENRIQUE AMOROCHO CORTEZ | C2: MUEBLES CC CUBRIMIENTOS | D2: 0 | F2: 2024-09-25 | G2: 2024-10-05 | H2: 2024-10-08 09:54:52 | I2: 0000-00-00 00:00:00 | J2: 2024-10-15 00:04:14 | K2: 2024-10-15 14:12:21 | L2: 0000-00-00 00:00:00 | M2: 2024-10-08 | N2: 2024-10-08 | O2: 2024-10-10 | P2: 2024-10-11 | Q2: 2024-10-11 | R2: Aprobado Despachos | S2: Bogota | T2: 98731 | U2: ACOPLE DESPL. SUP. MASTIL. SOMBR. ROMA. | X2: 1 | Y2: 0 | Z2: 0 | AA2: 0 | AB2: 33400 | AC2: FINALIZADO | AD2: =+VLOOKUP(T2,items!$A$2:$D$1255,4,0) -> 0 | AE2: =+VLOOKUP(T2,Tabla1[],5,0) -> 0 | AF2: =+MONTH(O2) -> 10
A3: 13209 | B3: ENRIQUE AMOROCHO CORTEZ | C3: MUEBLES CC CUBRIMIENTOS | D3: 0 | F3: 2024-09-25 | G3: 2024-10-05 | H3: 2024-10-08 09:54:52 | I3: 0000-00-00 00:00:00 | J3: 2024-10-15 00:04:14 | K3: 2024-10-15 14:12:21 | L3: 0000-00-00 00:00:00 | M3: 2024-10-08 | N3: 2024-10-08 | O3: 2024-10-10 | P3: 2024-10-11 | Q3: 2024-10-11 | R3: Aprobado Despachos | S3: Bogota | T3: REP045 | U3: REPARACION SOMBRILLA MANO OBRA | X3: 1 | Y3: 0 | Z3: 0 | AA3: 0 | AB3: 280000 | AC3: FINALIZADO | AD3: =+VLOOKUP(T3,items!$A$2:$D$1255,4,0) -> 0 | AE3: =+VLOOKUP(T3,Tabla1[],5,0) -> 0 | AF3: =+MONTH(O3) -> 10
A4: 13209 | B4: ENRIQUE AMOROCHO CORTEZ | C4: MUEBLES CC CUBRIMIENTOS | D4: 0 | F4: 2024-09-25 | G4: 2024-10-05 | H4: 2024-10-08 09:54:52 | I4: 0000-00-00 00:00:00 | J4: 2024-10-15 00:04:14 | K4: 2024-10-15 14:12:21 | L4: 0000-00-00 00:00:00 | M4: 2024-10-08 | N4: 2024-10-08 | O4: 2024-10-10 | P4: 2024-10-11 | Q4: 2024-10-11 | R4: Aprobado Despachos | S4: Bogota | T4: SERV08 | U4: SERVICIO VIATICOSINSTALACION MUEBLES | X4: 1 | Y4: 0 | Z4: 0 | AA4: 0 | AB4: 150000 | AC4: FINALIZADO | AD4: =+VLOOKUP(T4,items!$A$2:$D$1255,4,0) -> #N/A | AE4: =+VLOOKUP(T4,Tabla1[],5,0) -> #N/A | AF4: =+MONTH(O4) -> 10
A5: 52365 | B5: JORGE VASQUEZ | C5: MUEBLES CC CUBRIMIENTOS | D5: 0 | F5: 2025-06-04 | G5: 2025-06-04 | H5: 2020-07-06 09:16:22 | I5: 0000-00-00 00:00:00 | J5: 2020-08-03 10:09:35 | K5: 2020-08-03 10:10:06 | L5: 2020-11-13 11:37:46 | M5: 2020-07-03 | N5: 2020-07-07 | O5: 2020-07-30 | P5: 2020-08-04 | Q5: 2020-08-06 | R5: Aprobado Instalación | S5: Medellin | T5: 15477 | U5: MESA DE CENTRO JAPON ALUTECA 1*1(TA) | V5: No Aplica | X5: 1 | Y5: 0 | Z5: 0 | AA5: 0 | AB5: 1848739 | AC5: FINALIZADO | AD5: =+VLOOKUP(T5,items!$A$2:$D$1255,4,0) -> MUEBLES | AE5: =+VLOOKUP(T5,Tabla1[],5,0) -> 0 | AF5: =+MONTH(O5) -> 7
A6: 52365 | B6: JORGE VASQUEZ | C6: MUEBLES CC CUBRIMIENTOS | D6: 0 | F6: 2025-06-04 | G6: 2025-06-04 | H6: 2020-07-06 09:16:22 | I6: 0000-00-00 00:00:00 | J6: 2020-08-03 10:09:35 | K6: 2020-08-03 10:10:06 | L6: 2020-11-13 11:37:46 | M6: 2020-07-03 | N6: 2020-07-07 | O6: 2020-07-30 | P6: 2020-08-04 | Q6: 2020-08-06 | R6: Aprobado Instalación | S6: Medellin | T6: 15479 | U6: SOFA JAPON ALUTECA TRES PUESTOS C/C | V6: No Aplica | X6: 1 | Y6: 0 | Z6: 0 | AA6: 0 | AB6: 4075630 | AC6: FINALIZADO | AD6: =+VLOOKUP(T6,items!$A$2:$D$1255,4,0) -> MUEBLES | AE6: =+VLOOKUP(T6,Tabla1[],5,0) -> 0 | AF6: =+MONTH(O6) -> 7
A7: 52365 | B7: JORGE VASQUEZ | C7: MUEBLES CC CUBRIMIENTOS | D7: 0 | F7: 2025-06-04 | G7: 2025-06-04 | H7: 2020-07-06 09:16:22 | I7: 0000-00-00 00:00:00 | J7: 2020-08-03 10:09:35 | K7: 2020-08-03 10:10:06 | L7: 2020-11-13 11:37:46 | M7: 2020-07-03 | N7: 2020-07-07 | O7: 2020-07-30 | P7: 2020-08-04 | Q7: 2020-08-06 | R7: Aprobado Instalación | S7: Medellin | T7: 15481 | U7: POLTRONA JAPON ALUTECA C/C | V7: No Aplica | X7: 2 | Y7: 0 | Z7: 0 | AA7: 0 | AB7: 5294118 | AC7: FINALIZADO | AD7: =+VLOOKUP(T7,items!$A$2:$D$1255,4,0) -> MUEBLES | AE7: =+VLOOKUP(T7,Tabla1[],5,0) -> 0 | AF7: =+MONTH(O7) -> 7
A8: 52365 | B8: JORGE VASQUEZ | C8: MUEBLES CC CUBRIMIENTOS | D8: 0 | F8: 2025-06-04 | G8: 2025-06-04 | H8: 2020-07-06 09:16:22 | I8: 0000-00-00 00:00:00 | J8: 2020-08-03 10:09:35 | K8: 2020-08-03 10:10:06 | L8: 2020-11-13 11:37:46 | M8: 2020-07-03 | N8: 2020-07-07 | O8: 2020-07-30 | P8: 2020-08-04 | Q8: 2020-08-06 | R8: Aprobado Instalación | S8: Medellin | T8: 17 | U8: FLETES | V8: No Aplica | X8: 1 | Y8: 0 | Z8: 0 | AA8: 0 | AB8: 0 | AC8: FINALIZADO | AD8: =+VLOOKUP(T8,items!$A$2:$D$1255,4,0) -> #N/A | AE8: =+VLOOKUP(T8,Tabla1[],5,0) -> #N/A | AF8: =+MONTH(O8) -> 7
A9: 53753 | B9: PLAZA LA SERREZUELA SAS | C9: CUBRIMIENTO | D9: 0 | F9: 2025-01-17 | G9: 2025-02-26 | H9: 2025-03-21 14:00:31 | I9: 2025-04-12 07:35:14 | J9: 2025-04-24 11:45:42 | K9: 2025-04-28 08:23:55 | L9: 2025-08-20 09:23:51 | M9: 2025-03-05 | N9: 2025-04-10 | O9: 2025-04-24 | P9: 2025-04-30 | Q9: 2025-05-10 | R9: Aprobado Instalación | S9: Barranquilla | T9: 19353 | U9: PASADOR PUERTA CONICO P/FLEXIGLASS | X9: 2 | Y9: 0 | Z9: 0 | AA9: 0 | AB9: 5000 | AC9: FINALIZADO | AD9: =+VLOOKUP(T9,items!$A$2:$D$1255,4,0) -> 0 | AE9: =+VLOOKUP(T9,Tabla1[],5,0) -> 0 | AF9: =+MONTH(O9) -> 4
A10: 53753 | B10: PLAZA LA SERREZUELA SAS | C10: CUBRIMIENTO | D10: 0 | F10: 2025-01-17 | G10: 2025-02-26 | H10: 2025-03-21 14:00:31 | I10: 2025-04-12 07:35:14 | J10: 2025-04-24 11:45:42 | K10: 2025-04-28 08:23:55 | L10: 2025-08-20 09:23:51 | M10: 2025-03-05 | N10: 2025-04-10 | O10: 2025-04-24 | P10: 2025-04-30 | Q10: 2025-05-10 | R10: Aprobado Instalación | S10: Barranquilla | T10: FGLASS01 | U10: FLEXIGLASS 10 mm | W10: Blanco Señal - RAL 9003 | X10: 1 | Y10: 1500 | Z10: 3000 | AA10: 0 | AB10: 3703617 | AC10: FINALIZADO | AD10: =+VLOOKUP(T10,items!$A$2:$D$1255,4,0) -> FLEXIGLASS | AE10: =+VLOOKUP(T10,Tabla1[],5,0) -> 0 | AF10: =+MONTH(O10) -> 4
A11: 53753 | B11: PLAZA LA SERREZUELA SAS | C11: CUBRIMIENTO | D11: 0 | F11: 2025-01-17 | G11: 2025-02-26 | H11: 2025-03-21 14:00:31 | I11: 2025-04-12 07:35:14 | J11: 2025-04-24 11:45:42 | K11: 2025-04-28 08:23:55 | L11: 2025-08-20 09:23:51 | M11: 2025-03-05 | N11: 2025-04-10 | O11: 2025-04-24 | P11: 2025-04-30 | Q11: 2025-05-10 | R11: Aprobado Instalación | S11: Barranquilla | T11: FGLASS01 | U11: FLEXIGLASS 10 mm | W11: Blanco Señal - RAL 9003 | X11: 1 | Y11: 1500 | Z11: 3000 | AA11: 0 | AB11: 3703617 | AC11: FINALIZADO | AD11: =+VLOOKUP(T11,items!$A$2:$D$1255,4,0) -> FLEXIGLASS | AE11: =+VLOOKUP(T11,Tabla1[],5,0) -> 0 | AF11: =+MONTH(O11) -> 4
A12: 53753 | B12: PLAZA LA SERREZUELA SAS | C12: CUBRIMIENTO | D12: 0 | F12: 2025-01-17 | G12: 2025-02-26 | H12: 2025-03-21 14:00:31 | I12: 2025-04-12 07:35:14 | J12: 2025-04-24 11:45:42 | K12: 2025-04-28 08:23:55 | L12: 2025-08-20 09:23:51 | M12: 2025-03-05 | N12: 2025-04-10 | O12: 2025-04-24 | P12: 2025-04-30 | Q12: 2025-05-10 | R12: Aprobado Instalación | S12: Barranquilla | T12: SERV03 | U12: SERVICIO VIATICOSINSTALACION CUBRIMIENT | X12: 1 | Y12: 0 | Z12: 0 | AA12: 0 | AB12: 3400000 | AC12: FINALIZADO | AD12: =+VLOOKUP(T12,items!$A$2:$D$1255,4,0) -> #N/A | AE12: =+VLOOKUP(T12,Tabla1[],5,0) -> #N/A | AF12: =+MONTH(O12) -> 4
A13: 59320 | B13: JOSE PRUEBA MALDONADO PRUEBA | C13: MUEBLES CC CUBRIMIENTOS | D13: 0 | F13: 2025-07-16 | G13: 2025-03-04 | H13: 2025-04-29 10:34:59 | I13: 2025-04-29 11:05:19 | J13: 2025-04-30 15:57:46 | K13: 2025-04-29 13:34:55 | L13: 2025-04-29 13:35:01 | M13: 2025-03-05 | N13: 2025-03-13 | O13: 2025-04-08 | P13: 2025-04-10 | Q13: 2025-04-18 | R13: COTIZADO | S13: Cali | T13: 2043 | U13: MESA BISTRO 0.70*0.70 C/BM (TL) | W13: Color Aluminio Anodizado - RAL 9006 | X13: 1 | Y13: 0 | Z13: 0 | AA13: 0 | AB13: 883696 | AC13: FINALIZADO | AD13: =+VLOOKUP(T13,items!$A$2:$D$1255,4,0) -> MUEBLES | AE13: =+VLOOKUP(T13,Tabla1[],5,0) -> 0 | AF13: =+MONTH(O13) -> 4
A14: 59320 | B14: JOSE PRUEBA MALDONADO PRUEBA | C14: MUEBLES CC CUBRIMIENTOS | D14: 0 | F14: 2025-07-16 | G14: 2025-03-04 | H14: 2025-04-29 10:34:59 | I14: 2025-04-29 11:05:19 | J14: 2025-04-30 15:57:46 | K14: 2025-04-29 13:34:55 | L14: 2025-04-29 13:35:01 | M14: 2025-03-05 | N14: 2025-03-13 | O14: 2025-04-08 | P14: 2025-04-10 | Q14: 2025-04-18 | R14: COTIZADO | S14: Cali | T14: 2043 | U14: MESA BISTRO 0.70*0.70 C/BM (TL) | W14: Color Aluminio Anodizado - RAL 9006 | X14: 1 | Y14: 0 | Z14: 0 | AA14: 0 | AB14: 883696 | AC14: FINALIZADO | AD14: =+VLOOKUP(T14,items!$A$2:$D$1255,4,0) -> MUEBLES | AE14: =+VLOOKUP(T14,Tabla1[],5,0) -> 0 | AF14: =+MONTH(O14) -> 4
A15: 59320 | B15: JOSE PRUEBA MALDONADO PRUEBA | C15: MUEBLES CC CUBRIMIENTOS | D15: 0 | F15: 2025-07-16 | G15: 2025-03-04 | H15: 2025-04-29 10:34:59 | I15: 2025-04-29 11:05:19 | J15: 2025-04-30 15:57:46 | K15: 2025-04-29 13:34:55 | L15: 2025-04-29 13:35:01 | M15: 2025-03-05 | N15: 2025-03-13 | O15: 2025-04-08 | P15: 2025-04-10 | Q15: 2025-04-18 | R15: COTIZADO | S15: Cali | T15: PFAT07 | U15: PERGOLA FIJA ACEROTECA GRANDE | W15: Negro Señales - RAL 9004 | X15: 1 | Y15: 6000 | Z15: 0 | AA15: 4000 | AB15: 27803358 | AC15: FINALIZADO | AD15: =+VLOOKUP(T15,items!$A$2:$D$1255,4,0) -> PERGOLA | AE15: =+VLOOKUP(T15,Tabla1[],5,0) -> PERGOLA FIJA | AF15: =+MONTH(O15) -> 4
A16: 59320 | B16: JOSE PRUEBA MALDONADO PRUEBA | C16: MUEBLES CC CUBRIMIENTOS | D16: 0 | F16: 2025-07-16 | G16: 2025-03-04 | H16: 2025-04-29 10:34:59 | I16: 2025-04-29 11:05:19 | J16: 2025-04-30 15:57:46 | K16: 2025-04-29 13:34:55 | L16: 2025-04-29 13:35:01 | M16: 2025-03-05 | N16: 2025-03-13 | O16: 2025-04-08 | P16: 2025-04-10 | Q16: 2025-04-18 | R16: COTIZADO | S16: Cali | T16: PLAM05 | U16: MAXI PERGOLAM CON POSTES | W16: Aluminio Anodizado | X16: 1 | Y16: 5000 | Z16: 0 | AA16: 5000 | AB16: 71526140 | AC16: FINALIZADO | AD16: =+VLOOKUP(T16,items!$A$2:$D$1255,4,0) -> PERGOLA | AE16: =+VLOOKUP(T16,Tabla1[],5,0) -> MAXI PERGOLAM | AF16: =+MONTH(O16) -> 4
A17: 63598 | B17: hotel casablanca san andres sas | C17: CUBRIMIENTO | D17: 0 | F17: 2024-11-14 | G17: 2024-11-15 | H17: 2024-11-15 16:36:57 | I17: 0000-00-00 00:00:00 | J17: 2024-11-16 12:15:56 | K17: 2024-11-16 12:16:30 | L17: 0000-00-00 00:00:00 | M17: 2024-11-19 | N17: 2024-11-19 | O17: 2024-11-21 | P17: 2024-11-22 | Q17: 2024-11-22 | R17: Aprobado Facturacion | S17: Virtual | T17: 18013 | U17: TORN PRIS 8mmX8 DIAM P/FLEXIGLASS PLUS | X17: 190 | Y17: 0 | Z17: 0 | AA17: 0 | AB17: 237500 | AC17: FINALIZADO | AD17: =+VLOOKUP(T17,items!$A$2:$D$1255,4,0) -> 0 | AE17: =+VLOOKUP(T17,Tabla1[],5,0) -> 0 | AF17: =+MONTH(O17) -> 11
A18: 63598 | B18: hotel casablanca san andres sas | C18: CUBRIMIENTO | D18: 0 | F18: 2024-11-14 | G18: 2024-11-15 | H18: 2024-11-15 16:36:57 | I18: 0000-00-00 00:00:00 | J18: 2024-11-16 12:15:56 | K18: 2024-11-16 12:16:30 | L18: 0000-00-00 00:00:00 | M18: 2024-11-19 | N18: 2024-11-19 | O18: 2024-11-21 | P18: 2024-11-22 | Q18: 2024-11-22 | R18: Aprobado Facturacion | S18: Virtual | T18: 18447 | U18: FG+STACION SUPERIOR PUERTA (DAP1720) | X18: 2 | Y18: 0 | Z18: 0 | AA18: 0 | AB18: 9000 | AC18: FINALIZADO | AD18: =+VLOOKUP(T18,items!$A$2:$D$1255,4,0) -> 0 | AE18: =+VLOOKUP(T18,Tabla1[],5,0) -> 0 | AF18: =+MONTH(O18) -> 11
A19: 63598 | B19: hotel casablanca san andres sas | C19: CUBRIMIENTO | D19: 0 | F19: 2024-11-14 | G19: 2024-11-15 | H19: 2024-11-15 16:36:57 | I19: 0000-00-00 00:00:00 | J19: 2024-11-16 12:15:56 | K19: 2024-11-16 12:16:30 | L19: 0000-00-00 00:00:00 | M19: 2024-11-19 | N19: 2024-11-19 | O19: 2024-11-21 | P19: 2024-11-22 | Q19: 2024-11-22 | R19: Aprobado Facturacion | S19: Virtual | T19: 18448 | U19: FG+ESTACION INFERIOR PUERTA (DAP1721) | X19: 2 | Y19: 0 | Z19: 0 | AA19: 0 | AB19: 9000 | AC19: FINALIZADO | AD19: =+VLOOKUP(T19,items!$A$2:$D$1255,4,0) -> 0 | AE19: =+VLOOKUP(T19,Tabla1[],5,0) -> 0 | AF19: =+MONTH(O19) -> 11
A20: 63598 | B20: hotel casablanca san andres sas | C20: CUBRIMIENTO | D20: 0 | F20: 2024-11-14 | G20: 2024-11-15 | H20: 2024-11-15 16:36:57 | I20: 0000-00-00 00:00:00 | J20: 2024-11-16 12:15:56 | K20: 2024-11-16 12:16:30 | L20: 0000-00-00 00:00:00 | M20: 2024-11-19 | N20: 2024-11-19 | O20: 2024-11-21 | P20: 2024-11-22 | Q20: 2024-11-22 | R20: Aprobado Facturacion | S20: Virtual | T20: 18451 | U20: FG+TAPA IZQUIERDA BLANCA (DAP1724) | X20: 50 | Y20: 0 | Z20: 0 | AA20: 0 | AB20: 412500 | AC20: FINALIZADO | AD20: =+VLOOKUP(T20,items!$A$2:$D$1255,4,0) -> 0 | AE20: =+VLOOKUP(T20,Tabla1[],5,0) -> 0 | AF20: =+MONTH(O20) -> 11
A21: 63598 | B21: hotel casablanca san andres sas | C21: CUBRIMIENTO | D21: 0 | F21: 2024-11-14 | G21: 2024-11-15 | H21: 2024-11-15 16:36:57 | I21: 0000-00-00 00:00:00 | J21: 2024-11-16 12:15:56 | K21: 2024-11-16 12:16:30 | L21: 0000-00-00 00:00:00 | M21: 2024-11-19 | N21: 2024-11-19 | O21: 2024-11-21 | P21: 2024-11-22 | Q21: 2024-11-22 | R21: Aprobado Facturacion | S21: Virtual | T21: 18452 | U21: FG+TAPA DERECHA BLANCA (DAP1725) | X21: 50 | Y21: 0 | Z21: 0 | AA21: 0 | AB21: 412500 | AC21: FINALIZADO | AD21: =+VLOOKUP(T21,items!$A$2:$D$1255,4,0) -> 0 | AE21: =+VLOOKUP(T21,Tabla1[],5,0) -> 0 | AF21: =+MONTH(O21) -> 11
A22: 63598 | B22: hotel casablanca san andres sas | C22: CUBRIMIENTO | D22: 0 | F22: 2024-11-14 | G22: 2024-11-15 | H22: 2024-11-15 16:36:57 | I22: 0000-00-00 00:00:00 | J22: 2024-11-16 12:15:56 | K22: 2024-11-16 12:16:30 | L22: 0000-00-00 00:00:00 | M22: 2024-11-19 | N22: 2024-11-19 | O22: 2024-11-21 | P22: 2024-11-22 | Q22: 2024-11-22 | R22: Aprobado Facturacion | S22: Virtual | T22: 18453 | U22: FG+CUADRANTE (DAP1726) | X22: 30 | Y22: 0 | Z22: 0 | AA22: 0 | AB22: 47400 | AC22: FINALIZADO | AD22: =+VLOOKUP(T22,items!$A$2:$D$1255,4,0) -> 0 | AE22: =+VLOOKUP(T22,Tabla1[],5,0) -> 0 | AF22: =+MONTH(O22) -> 11
A23: 63598 | B23: hotel casablanca san andres sas | C23: CUBRIMIENTO | D23: 0 | F23: 2024-11-14 | G23: 2024-11-15 | H23: 2024-11-15 16:36:57 | I23: 0000-00-00 00:00:00 | J23: 2024-11-16 12:15:56 | K23: 2024-11-16 12:16:30 | L23: 0000-00-00 00:00:00 | M23: 2024-11-19 | N23: 2024-11-19 | O23: 2024-11-21 | P23: 2024-11-22 | Q23: 2024-11-22 | R23: Aprobado Facturacion | S23: Virtual | T23: 18455 | U23: FG+ESTACION SUPERIOR (DAP1709) | X23: 2 | Y23: 0 | Z23: 0 | AA23: 0 | AB23: 9600 | AC23: FINALIZADO | AD23: =+VLOOKUP(T23,items!$A$2:$D$1255,4,0) -> 0 | AE23: =+VLOOKUP(T23,Tabla1[],5,0) -> 0 | AF23: =+MONTH(O23) -> 11
A24: 63598 | B24: hotel casablanca san andres sas | C24: CUBRIMIENTO | D24: 0 | F24: 2024-11-14 | G24: 2024-11-15 | H24: 2024-11-15 16:36:57 | I24: 0000-00-00 00:00:00 | J24: 2024-11-16 12:15:56 | K24: 2024-11-16 12:16:30 | L24: 0000-00-00 00:00:00 | M24: 2024-11-19 | N24: 2024-11-19 | O24: 2024-11-21 | P24: 2024-11-22 | Q24: 2024-11-22 | R24: Aprobado Facturacion | S24: Virtual | T24: 18456 | U24: RETENEDOR ESTACIONAM INF PUERTA(DAP1705) | X24: 2 | Y24: 0 | Z24: 0 | AA24: 0 | AB24: 4500 | AC24: FINALIZADO | AD24: =+VLOOKUP(T24,items!$A$2:$D$1255,4,0) -> 0 | AE24: =+VLOOKUP(T24,Tabla1[],5,0) -> 0 | AF24: =+MONTH(O24) -> 11
A25: 63598 | B25: hotel casablanca san andres sas | C25: CUBRIMIENTO | D25: 0 | F25: 2024-11-14 | G25: 2024-11-15 | H25: 2024-11-15 16:36:57 | I25: 0000-00-00 00:00:00 | J25: 2024-11-16 12:15:56 | K25: 2024-11-16 12:16:30 | L25: 0000-00-00 00:00:00 | M25: 2024-11-19 | N25: 2024-11-19 | O25: 2024-11-21 | P25: 2024-11-22 | Q25: 2024-11-22 | R25: Aprobado Facturacion | S25: Virtual | T25: 18457 | U25: FG+BUJE SUPERIOR (DAP1728) | X25: 30 | Y25: 0 | Z25: 0 | AA25: 0 | AB25: 66000 | AC25: FINALIZADO | AD25: =+VLOOKUP(T25,items!$A$2:$D$1255,4,0) -> 0 | AE25: =+VLOOKUP(T25,Tabla1[],5,0) -> 0 | AF25: =+MONTH(O25) -> 11
A26: 63598 | B26: hotel casablanca san andres sas | C26: CUBRIMIENTO | D26: 0 | F26: 2024-11-14 | G26: 2024-11-15 | H26: 2024-11-15 16:36:57 | I26: 0000-00-00 00:00:00 | J26: 2024-11-16 12:15:56 | K26: 2024-11-16 12:16:30 | L26: 0000-00-00 00:00:00 | M26: 2024-11-19 | N26: 2024-11-19 | O26: 2024-11-21 | P26: 2024-11-22 | Q26: 2024-11-22 | R26: Aprobado Facturacion | S26: Virtual | T26: 18458 | U26: FG+BUJE INFERIOR (DAP1729) | X26: 30 | Y26: 0 | Z26: 0 | AA26: 0 | AB26: 73500 | AC26: FINALIZADO | AD26: =+VLOOKUP(T26,items!$A$2:$D$1255,4,0) -> 0 | AE26: =+VLOOKUP(T26,Tabla1[],5,0) -> 0 | AF26: =+MONTH(O26) -> 11
A27: 63598 | B27: hotel casablanca san andres sas | C27: CUBRIMIENTO | D27: 0 | F27: 2024-11-14 | G27: 2024-11-15 | H27: 2024-11-15 16:36:57 | I27: 0000-00-00 00:00:00 | J27: 2024-11-16 12:15:56 | K27: 2024-11-16 12:16:30 | L27: 0000-00-00 00:00:00 | M27: 2024-11-19 | N27: 2024-11-19 | O27: 2024-11-21 | P27: 2024-11-22 | Q27: 2024-11-22 | R27: Aprobado Facturacion | S27: Virtual | T27: 19544 | U27: FG+BISAGRA PUERTA ZAMAK | X27: 30 | Y27: 0 | Z27: 0 | AA27: 0 | AB27: 375000 | AC27: FINALIZADO | AD27: =+VLOOKUP(T27,items!$A$2:$D$1255,4,0) -> 0 | AE27: =+VLOOKUP(T27,Tabla1[],5,0) -> 0 | AF27: =+MONTH(O27) -> 11
A28: 63598 | B28: hotel casablanca san andres sas | C28: CUBRIMIENTO | D28: 0 | F28: 2024-11-14 | G28: 2024-11-15 | H28: 2024-11-15 16:36:57 | I28: 0000-00-00 00:00:00 | J28: 2024-11-16 12:15:56 | K28: 2024-11-16 12:16:30 | L28: 0000-00-00 00:00:00 | M28: 2024-11-19 | N28: 2024-11-19 | O28: 2024-11-21 | P28: 2024-11-22 | Q28: 2024-11-22 | R28: Aprobado Facturacion | S28: Virtual | T28: 19545 | U28: FG+BISAGRA SUPERIOR ZAMAK | X28: 30 | Y28: 0 | Z28: 0 | AA28: 0 | AB28: 360000 | AC28: FINALIZADO | AD28: =+VLOOKUP(T28,items!$A$2:$D$1255,4,0) -> 0 | AE28: =+VLOOKUP(T28,Tabla1[],5,0) -> 0 | AF28: =+MONTH(O28) -> 11
... A32: 64066 | B32: Iveth Suarez | C32: CUBRIMIENTO | D32: 0 | F32: 2024-09-20 | G32: 2024-09-20 | H32: 2024-09-23 13:29:15 | I32: 0000-00-00 00:00:00 | J32: 2024-09-23 13:29:20 | K32: 2024-09-25 09:39:40 | L32: 0000-00-00 00:00:00 | M32: 2024-09-23 | N32: 2024-09-23 | O32: 2024-09-25 | P32: 2024-09-26 | Q32: 2024-09-26 | R32: Aprobado Despachos | S32: Toscany | T32: 644041 | U32: FURNISCREEN GRIS 2M EB4027W G8 625GR | X32: 5 | Y32: 0 | Z32: 0 | AA32: 0 | AB32: 780000 | AC32: FINALIZADO | AD32: =+VLOOKUP(T32,items!$A$2:$D$1255,4,0) -> 0 | AE32: =+VLOOKUP(T32,Tabla1[],5,0) -> 0 | AF32: =+MONTH(O32) -> 9
A33: 68739 | B33: SERGIO DAZA | C33: MUEBLES CC CUBRIMIENTOS | D33: 0 | F33: 2022-01-29 | G33: 2025-10-16 | H33: 2025-10-23 13:52:43 | I33: 0000-00-00 00:00:00 | J33: 0000-00-00 00:00:00 | K33: 0000-00-00 00:00:00 | L33: 0000-00-00 00:00:00 | M33: 2025-10-17 | N33: 2025-10-17 | O33: 2025-11-12 | P33: 0000-00-00 | Q33: 2025-11-18 | R33: Aprobado Comercial | S33: Virtual | T33: 15477 | U33: MESA DE CENTRO JAPON ALUTECA 1*1(TA) | W33: Aluminio Anodizado | X33: 1 | Y33: 0 | Z33: 0 | AA33: 0 | AB33: 1754159 | AC33: DISEÑO | AD33: =+VLOOKUP(T33,items!$A$2:$D$1255,4,0) -> MUEBLES | AE33: =+VLOOKUP(T33,Tabla1[],5,0) -> 0 | AF33: =+MONTH(O33) -> 11
A34: 73280 | B34: D L K S.A.S. | C34: CUBRIMIENTO | D34: 0 | F34: 2023-11-28 | G34: 2024-11-15 | H34: 2024-11-27 10:39:54 | I34: 2024-11-30 15:09:29 | J34: 2025-02-16 19:07:50 | K34: 2025-02-25 08:19:00 | L34: 2025-04-23 11:08:04 | M34: 2024-11-27 | N34: 2024-12-07 | O34: 2025-02-23 | P34: 2025-02-26 | Q34: 2025-04-22 | R34: Aprobado Instalación | S34: Bogota | T34: 18076 | U34: SPOT ANTIGUO BLANCO / 3000K / 110V / 3W | X34: 15 | Y34: 0 | Z34: 0 | AA34: 0 | AB34: 1211250 | AC34: FINALIZADO | AD34: =+VLOOKUP(T34,items!$A$2:$D$1255,4,0) -> 0 | AE34: =+VLOOKUP(T34,Tabla1[],5,0) -> 0 | AF34: =+MONTH(O34) -> 2
A35: 73280 | B35: D L K S.A.S. | C35: CUBRIMIENTO | D35: 0 | F35: 2023-11-28 | G35: 2024-11-15 | H35: 2024-11-27 10:39:54 | I35: 2024-11-30 15:09:29 | J35: 2025-02-16 19:07:50 | K35: 2025-02-25 08:19:00 | L35: 2025-04-23 11:08:04 | M35: 2024-11-27 | N35: 2024-12-07 | O35: 2025-02-23 | P35: 2025-02-26 | Q35: 2025-04-22 | R35: Aprobado Instalación | S35: Bogota | T35: CAMBIO LONA 02 | U35: CAMBIO LONA PVC TOLDO FIJO | V35: LONA PERGOTEX TRASLUCIDA BLANCA 3M | X35: 1 | Y35: 13500 | Z35: 0 | AA35: 2500 | AB35: 8103344 | AC35: FINALIZADO | AD35: =+VLOOKUP(T35,items!$A$2:$D$1255,4,0) -> 0 | AE35: =+VLOOKUP(T35,Tabla1[],5,0) -> 0 | AF35: =+MONTH(O35) -> 2
A36: 73280 | B36: D L K S.A.S. | C36: CUBRIMIENTO | D36: 0 | F36: 2023-11-28 | G36: 2024-11-15 | H36: 2024-11-27 10:39:54 | I36: 2024-11-30 15:09:29 | J36: 2025-02-16 19:07:50 | K36: 2025-02-25 08:19:00 | L36: 2025-04-23 11:08:04 | M36: 2024-11-27 | N36: 2024-12-07 | O36: 2025-02-23 | P36: 2025-02-26 | Q36: 2025-04-22 | R36: Aprobado Instalación | S36: Bogota | T36: LONA PERGOTEK ESPECIAL02 | U36: LONA ESPECIAL PERGOTEK L13500 P5800 | V36: LONA PERGOTEX TRASLUCIDA BLANCA 3M | X36: 1 | Y36: 13500 | Z36: 0 | AA36: 5800 | AB36: 16988243 | AC36: FINALIZADO | AD36: =+VLOOKUP(T36,items!$A$2:$D$1255,4,0) -> 0 | AE36: =+VLOOKUP(T36,Tabla1[],5,0) -> 0 | AF36: =+MONTH(O36) -> 2
A37: 73280 | B37: D L K S.A.S. | C37: CUBRIMIENTO | D37: 0 | F37: 2023-11-28 | G37: 2024-11-15 | H37: 2024-11-27 10:39:54 | I37: 2024-11-30 15:09:29 | J37: 2025-02-16 19:07:50 | K37: 2025-02-25 08:19:00 | L37: 2025-04-23 11:08:04 | M37: 2024-11-27 | N37: 2024-12-07 | O37: 2025-02-23 | P37: 2025-02-26 | Q37: 2025-04-22 | R37: Aprobado Instalación | S37: Bogota | T37: SERV03 | U37: SERVICIO VIATICOS-INSTALACION CUBRIMIENT | X37: 1 | Y37: 0 | Z37: 0 | AA37: 0 | AB37: 1710000 | AC37: FINALIZADO | AD37: =+VLOOKUP(T37,items!$A$2:$D$1255,4,0) -> #N/A | AE37: =+VLOOKUP(T37,Tabla1[],5,0) -> #N/A | AF37: =+MONTH(O37) -> 2
A38: 73280 | B38: D L K S.A.S. | C38: CUBRIMIENTO | D38: 0 | F38: 2023-11-28 | G38: 2024-11-15 | H38: 2024-11-27 10:39:54 | I38: 2024-11-30 15:09:29 | J38: 2025-02-16 19:07:50 | K38: 2025-02-25 08:19:00 | L38: 2025-04-23 11:08:04 | M38: 2024-11-27 | N38: 2024-12-07 | O38: 2025-02-23 | P38: 2025-02-26 | Q38: 2025-04-22 | R38: Aprobado Instalación | S38: Bogota | T38: SERV03 | U38: SERVICIO VIATICOS-INSTALACION CUBRIMIENT | X38: 1 | Y38: 0 | Z38: 0 | AA38: 0 | AB38: 4132500 | AC38: FINALIZADO | AD38: =+VLOOKUP(T38,items!$A$2:$D$1255,4,0) -> #N/A | AE38: =+VLOOKUP(T38,Tabla1[],5,0) -> #N/A | AF38: =+MONTH(O38) -> 2
A39: 73517 | B39: LLANO DOMINGUEZ LTDA AGENCIA DE SEGUROS | C39: MUEBLES CC CUBRIMIENTOS | D39: 0 | F39: 2022-08-01 | G39: 2024-05-16 | H39: 2024-05-20 11:04:29 | I39: 0000-00-00 00:00:00 | J39: 2024-06-12 16:56:31 | K39: 2024-06-13 15:39:50 | L39: 2024-07-18 13:22:19 | M39: 2024-05-20 | N39: 2024-05-20 | O39: 2024-06-13 | P39: 2024-06-18 | Q39: 2024-06-20 | R39: Aprobado Instalación | S39: Virtual | T39: 5325 | U39: BASE METALI SOMBRILLA 400*400EN3/16"M38 | W39: Chocolate - RAL 8017 | X39: 1 | Y39: 0 | Z39: 0 | AA39: 0 | AB39: 321608 | AC39: FINALIZADO | AD39: =+VLOOKUP(T39,items!$A$2:$D$1255,4,0) -> 0 | AE39: =+VLOOKUP(T39,Tabla1[],5,0) -> 0 | AF39: =+MONTH(O39) -> 6
A40: 73517 | B40: LLANO DOMINGUEZ LTDA AGENCIA DE SEGUROS | C40: MUEBLES CC CUBRIMIENTOS | D40: 0 | F40: 2022-08-01 | G40: 2024-05-16 | H40: 2024-05-20 11:04:29 | I40: 0000-00-00 00:00:00 | J40: 2024-06-12 16:56:31 | K40: 2024-06-13 15:39:50 | L40: 2024-07-18 13:22:19 | M40: 2024-05-20 | N40: 2024-05-20 | O40: 2024-06-13 | P40: 2024-06-18 | Q40: 2024-06-20 | R40: Aprobado Instalación | S40: Virtual | T40: 8867 | U40: LONA SOMBRILLA TROPICAL 2.7 6P S/FLE | V40: LONA DICKSON ROJO VINOTINTO REF:3914 | X40: 1 | Y40: 0 | Z40: 0 | AA40: 0 | AB40: 1200000 | AC40: FINALIZADO | AD40: =+VLOOKUP(T40,items!$A$2:$D$1255,4,0) -> 0 | AE40: =+VLOOKUP(T40,Tabla1[],5,0) -> 0 | AF40: =+MONTH(O40) -> 6
A41: 73517 | B41: LLANO DOMINGUEZ LTDA AGENCIA DE SEGUROS | C41: MUEBLES CC CUBRIMIENTOS | D41: 0 | F41: 2022-08-01 | G41: 2024-05-16 | H41: 2024-05-20 11:04:29 | I41: 0000-00-00 00:00:00 | J41: 2024-06-12 16:56:31 | K41: 2024-06-13 15:39:50 | L41: 2024-07-18 13:22:19 | M41: 2024-05-20 | N41: 2024-05-20 | O41: 2024-06-13 | P41: 2024-06-18 | Q41: 2024-06-20 | R41: Aprobado Instalación | S41: Virtual | T41: REP023 | U41: REPARACION ESTRUCT SOMBRILLA MAT PRIMA | X41: 1 | Y41: 0 | Z41: 0 | AA41: 0 | AB41: 450000 | AC41: FINALIZADO | AD41: =+VLOOKUP(T41,items!$A$2:$D$1255,4,0) -> 0 | AE41: =+VLOOKUP(T41,Tabla1[],5,0) -> 0 | AF41: =+MONTH(O41) -> 6
A42: 73517 | B42: LLANO DOMINGUEZ LTDA AGENCIA DE SEGUROS | C42: MUEBLES CC CUBRIMIENTOS | D42: 0 | F42: 2022-08-01 | G42: 2024-05-16 | H42: 2024-05-20 11:04:29 | I42: 0000-00-00 00:00:00 | J42: 2024-06-12 16:56:31 | K42: 2024-06-13 15:39:50 | L42: 2024-07-18 13:22:19 | M42: 2024-05-20 | N42: 2024-05-20 | O42: 2024-06-13 | P42: 2024-06-18 | Q42: 2024-06-20 | R42: Aprobado Instalación | S42: Virtual | T42: REP031 | U42: REPARACION MESA MAT PRIMA | X42: 1 | Y42: 0 | Z42: 0 | AA42: 0 | AB42: 650000 | AC42: FINALIZADO | AD42: =+VLOOKUP(T42,items!$A$2:$D$1255,4,0) -> 0 | AE42: =+VLOOKUP(T42,Tabla1[],5,0) -> 0 | AF42: =+MONTH(O42) -> 6
A43: 73517 | B43: LLANO DOMINGUEZ LTDA AGENCIA DE SEGUROS | C43: MUEBLES CC CUBRIMIENTOS | D43: 0 | F43: 2022-08-01 | G43: 2024-05-16 | H43: 2024-05-20 11:04:29 | I43: 0000-00-00 00:00:00 | J43: 2024-06-12 16:56:31 | K43: 2024-06-13 15:39:50 | L43: 2024-07-18 13:22:19 | M43: 2024-05-20 | N43: 2024-05-20 | O43: 2024-06-13 | P43: 2024-06-18 | Q43: 2024-06-20 | R43: Aprobado Instalación | S43: Virtual | T43: REP040 | U43: REPARACION SILLA MAT PRIMA | X43: 4 | Y43: 0 | Z43: 0 | AA43: 0 | AB43: 1200000 | AC43: FINALIZADO | AD43: =+VLOOKUP(T43,items!$A$2:$D$1255,4,0) -> 0 | AE43: =+VLOOKUP(T43,Tabla1[],5,0) -> 0 | AF43: =+MONTH(O43) -> 6
A44: 75473 | B44: Tikkal Etapa I - Propiedad Horizontal | C44: MUEBLES CC CUBRIMIENTOS | D44: 0 | F44: 2022-10-04 | G44: 2024-06-17 | H44: 2024-06-17 12:04:58 | I44: 0000-00-00 00:00:00 | J44: 2024-07-06 16:14:21 | K44: 2024-07-09 13:26:13 | L44: 0000-00-00 00:00:00 | M44: 2024-06-18 | N44: 2024-06-18 | O44: 2024-06-25 | P44: 2024-07-01 | Q44: 2024-07-01 | R44: Aprobado Despachos | S44: Virtual | T44: 11487 | U44: MALLA ASOLEADORA SAKAI | V44: FURNISCREEN AZUL PT 2M EB4027W G8 625GR | X44: 8 | Y44: 0 | Z44: 0 | AA44: 0 | AB44: 1258448 | AC44: FINALIZADO | AD44: =+VLOOKUP(T44,items!$A$2:$D$1255,4,0) -> 0 | AE44: =+VLOOKUP(T44,Tabla1[],5,0) -> 0 | AF44: =+MONTH(O44) -> 6
A45: 75785 | B45: DECOSMART | C45: MUEBLES CC CUBRIMIENTOS | D45: 0 | F45: 2022-10-14 | G45: 2025-08-04 | H45: 2025-08-05 15:49:41 | I45: 0000-00-00 00:00:00 | J45: 2025-08-08 16:32:26 | K45: 2025-08-08 16:33:03 | L45: 2025-09-16 13:51:10 | M45: 2025-08-05 | N45: 2025-08-05 | O45: 2025-08-07 | P45: 2025-08-11 | Q45: 2025-08-13 | R45: Aprobado Instalación | S45: Virtual | T45: 6277 | U45: LONA PERGOTEX BLACKOUT BLANCA 3 M | X45: 1 | Y45: 0 | Z45: 0 | AA45: 0 | AB45: 250000 | AC45: FINALIZADO | AD45: =+VLOOKUP(T45,items!$A$2:$D$1255,4,0) -> 0 | AE45: =+VLOOKUP(T45,Tabla1[],5,0) -> 0 | AF45: =+MONTH(O45) -> 8
A46: 75785 | B46: DECOSMART | C46: MUEBLES CC CUBRIMIENTOS | D46: 0 | F46: 2022-10-14 | G46: 2025-08-04 | H46: 2025-08-05 15:49:41 | I46: 0000-00-00 00:00:00 | J46: 2025-08-08 16:32:26 | K46: 2025-08-08 16:33:03 | L46: 2025-09-16 13:51:10 | M46: 2025-08-05 | N46: 2025-08-05 | O46: 2025-08-07 | P46: 2025-08-11 | Q46: 2025-08-13 | R46: Aprobado Instalación | S46: Virtual | T46: SERV03 | U46: SERVICIO VIATICOSINSTALACION CUBRIMIENT | X46: 1 | Y46: 0 | Z46: 0 | AA46: 0 | AB46: 2511000 | AC46: FINALIZADO | AD46: =+VLOOKUP(T46,items!$A$2:$D$1255,4,0) -> #N/A | AE46: =+VLOOKUP(T46,Tabla1[],5,0) -> #N/A | AF46: =+MONTH(O46) -> 8
A47: 81831 | B47: D6 SEGUROS LTDA | C47: MUEBLES CC CUBRIMIENTOS | D47: 0 | F47: 2023-05-08 | G47: 2024-07-31 | H47: 2024-08-02 10:29:51 | I47: 0000-00-00 00:00:00 | J47: 2024-08-21 08:12:32 | K47: 2024-08-21 08:13:03 | L47: 2024-09-03 10:07:57 | M47: 2024-08-02 | N47: 2024-08-02 | O47: 2024-09-09 | P47: 2024-09-13 | Q47: 2024-09-17 | R47: Aprobado Instalación | S47: medellin | T47: 6752 | U47: FUNDA SOMBRILLA ROMA 3.0 X 3.0M | V47: LONAFLEX | X47: 1 | Y47: 0 | Z47: 0 | AA47: 0 | AB47: 371593 | AC47: FINALIZADO | AD47: =+VLOOKUP(T47,items!$A$2:$D$1255,4,0) -> FUNDA | AE47: =+VLOOKUP(T47,Tabla1[],5,0) -> 0 | AF47: =+MONTH(O47) -> 9
A48: 82760 | B48: Arte Patio NEW QUOTE: SERENO RESD. RETRACTABLES | C48: CUBRIMIENTO | D48: 0 | F48: 2023-06-02 | G48: 2025-02-17 | H48: 2025-02-18 11:01:56 | I48: 2025-03-10 17:02:09 | J48: 2025-03-13 09:20:27 | K48: 2025-03-28 09:09:05 | L48: 2025-04-09 17:08:05 | M48: 2025-02-19 | N48: 2025-03-03 | O48: 2025-03-13 | P48: 2025-03-17 | Q48: 2025-03-27 | R48: Aprobado Instalación | S48: Toscana | T48: PTEKROM12 | U48: PERGOTEK ROMANO MINI MUROS | V48: LONA PERGOTEX TRASLUCIDA BLANCA 3M | W48: Blanco Señal - RAL 9003 | X48: 1 | Y48: 3735 | Z48: 0 | AA48: 3656 | AB48: 12414120 | AC48: FINALIZADO | AD48: =+VLOOKUP(T48,items!$A$2:$D$1255,4,0) -> PERGOLA | AE48: =+VLOOKUP(T48,Tabla1[],5,0) -> PERGOTEK ROMANO | AF48: =+MONTH(O48) -> 3 | AG48: 3816 | AH48: 12414120
A49: 82760 | B49: Arte Patio NEW QUOTE: SERENO RESD. RETRACTABLES | C49: CUBRIMIENTO | D49: 0 | F49: 2023-06-02 | G49: 2025-02-17 | H49: 2025-02-18 11:01:56 | I49: 2025-03-10 17:02:09 | J49: 2025-03-13 09:20:27 | K49: 2025-03-28 09:09:05 | L49: 2025-04-09 17:08:05 | M49: 2025-02-19 | N49: 2025-03-03 | O49: 2025-03-13 | P49: 2025-03-17 | Q49: 2025-03-27 | R49: Aprobado Instalación | S49: Toscana | T49: PTEKROM12 | U49: PERGOTEK ROMANO MINI MUROS | V49: LONA PERGOTEX TRASLUCIDA BLANCA 3M | W49: Blanco Señal - RAL 9003 | X49: 1 | Y49: 3734 | Z49: 0 | AA49: 4318 | AB49: 13243802 | AC49: FINALIZADO | AD49: =+VLOOKUP(T49,items!$A$2:$D$1255,4,0) -> PERGOLA | AE49: =+VLOOKUP(T49,Tabla1[],5,0) -> PERGOTEK ROMANO | AF49: =+MONTH(O49) -> 3 | AG49: 3816 | AH49: 13243802
A50: 82760 | B50: Arte Patio NEW QUOTE: SERENO RESD. RETRACTABLES | C50: CUBRIMIENTO | D50: 0 | F50: 2023-06-02 | G50: 2025-02-17 | H50: 2025-02-18 11:01:56 | I50: 2025-03-10 17:02:09 | J50: 2025-03-13 09:20:27 | K50: 2025-03-28 09:09:05 | L50: 2025-04-09 17:08:05 | M50: 2025-02-19 | N50: 2025-03-03 | O50: 2025-03-13 | P50: 2025-03-17 | Q50: 2025-03-27 | R50: Aprobado Instalación | S50: Toscana | T50: PTEKROM12 | U50: PERGOTEK ROMANO MINI MUROS | V50: LONA PERGOTEX TRASLUCIDA BLANCA 3M | W50: Blanco Señal - RAL 9003 | X50: 1 | Y50: 3734 | Z50: 0 | AA50: 4228 | AB50: 13243802 | AC50: FINALIZADO | AD50: =+VLOOKUP(T50,items!$A$2:$D$1255,4,0) -> PERGOLA | AE50: =+VLOOKUP(T50,Tabla1[],5,0) -> PERGOTEK ROMANO | AF50: =+MONTH(O50) -> 3 | AG50: 3816 | AH50: 13243802
A51: 82760 | B51: Arte Patio NEW QUOTE: SERENO RESD. RETRACTABLES | C51: CUBRIMIENTO | D51: 0 | F51: 2023-06-02 | G51: 2025-02-17 | H51: 2025-02-18 11:01:56 | I51: 2025-03-10 17:02:09 | J51: 2025-03-13 09:20:27 | K51: 2025-03-28 09:09:05 | L51: 2025-04-09 17:08:05 | M51: 2025-02-19 | N51: 2025-03-03 | O51: 2025-03-13 | P51: 2025-03-17 | Q51: 2025-03-27 | R51: Aprobado Instalación | S51: Toscana | T51: PTEKROM12 | U51: PERGOTEK ROMANO MINI MUROS | V51: LONA PERGOTEX TRASLUCIDA BLANCA 3M | W51: Blanco Señal - RAL 9003 | X51: 1 | Y51: 3734 | Z51: 0 | AA51: 4265 | AB51: 13243802 | AC51: FINALIZADO | AD51: =+VLOOKUP(T51,items!$A$2:$D$1255,4,0) -> PERGOLA | AE51: =+VLOOKUP(T51,Tabla1[],5,0) -> PERGOTEK ROMANO | AF51: =+MONTH(O51) -> 3 | AG51: 3816 | AH51: 13243802
A52: 82760 | B52: Arte Patio NEW QUOTE: SERENO RESD. RETRACTABLES | C52: CUBRIMIENTO | D52: 0 | F52: 2023-06-02 | G52: 2025-02-17 | H52: 2025-02-18 11:01:56 | I52: 2025-03-10 17:02:09 | J52: 2025-03-13 09:20:27 | K52: 2025-03-28 09:09:05 | L52: 2025-04-09 17:08:05 | M52: 2025-02-19 | N52: 2025-03-03 | O52: 2025-03-13 | P52: 2025-03-17 | Q52: 2025-03-27 | R52: Aprobado Instalación | S52: Toscana | T52: PTEKROM12 | U52: PERGOTEK ROMANO MINI MUROS | V52: LONA PERGOTEX TRASLUCIDA BLANCA 3M | W52: Blanco Señal - RAL 9003 | X52: 1 | Y52: 3735 | Z52: 0 | AA52: 3630 | AB52: 12414120 | AC52: FINALIZADO | AD52: =+VLOOKUP(T52,items!$A$2:$D$1255,4,0) -> PERGOLA | AE52: =+VLOOKUP(T52,Tabla1[],5,0) -> PERGOTEK ROMANO | AF52: =+MONTH(O52) -> 3 | AG52: 3816 | AH52: 12414120
A53: 84537 | B53: LEONARDO MANRIQUE GOMEZ | C53: MUEBLES CC CUBRIMIENTOS | D53: 0 | F53: 2023-08-02 | G53: 2025-10-31 | H53: 0000-00-00 00:00:00 | I53: 0000-00-00 00:00:00 | J53: 0000-00-00 00:00:00 | K53: 0000-00-00 00:00:00 | L53: 0000-00-00 00:00:00 | M53: 2025-11-03 | N53: 2025-11-03 | O53: 2025-11-17 | P53: 2025-11-19 | Q53: 2025-11-21 | R53: Detenido Comercial | S53: Cali | T53: SERV06 | U53: SERVICIO MTTO/REPARACION MUEBLES | X53: 1 | Y53: 0 | Z53: 0 | AA53: 0 | AB53: 1670000 | AC53: COMERCIAL | AD53: =+VLOOKUP(T53,items!$A$2:$D$1255,4,0) -> #N/A | AE53: =+VLOOKUP(T53,Tabla1[],5,0) -> #N/A | AF53: =+MONTH(O53) -> 11
A54: 84660 | B54: PETRONIO PéREZ ÁLVAREZ | C54: CUBRIMIENTO | D54: 0 | F54: 2023-08-15 | G54: 2024-05-23 | H54: 2024-05-24 09:27:31 | I54: 0000-00-00 00:00:00 | J54: 2024-05-26 23:35:29 | K54: 2024-05-27 16:13:26 | L54: 0000-00-00 00:00:00 | M54: 2024-05-27 | N54: 2024-05-27 | O54: 2024-05-28 | P54: 2024-05-31 | Q54: 2024-05-31 | R54: Aprobado Facturacion | S54: Cali | T54: 180331 | U54: CINTA ALUMINIO 25mmX33mts | X54: 12 | Y54: 0 | Z54: 0 | AA54: 0 | AB54: 146400 | AC54: FINALIZADO | AD54: =+VLOOKUP(T54,items!$A$2:$D$1255,4,0) -> 0 | AE54: =+VLOOKUP(T54,Tabla1[],5,0) -> 0 | AF54: =+MONTH(O54) -> 5
A55: 84660 | B55: PETRONIO PéREZ ÁLVAREZ | C55: CUBRIMIENTO | D55: 0 | F55: 2023-08-15 | G55: 2024-05-23 | H55: 2024-05-24 09:27:31 | I55: 0000-00-00 00:00:00 | J55: 2024-05-26 23:35:29 | K55: 2024-05-27 16:13:26 | L55: 0000-00-00 00:00:00 | M55: 2024-05-27 | N55: 2024-05-27 | O55: 2024-05-28 | P55: 2024-05-31 | Q55: 2024-05-31 | R55: Aprobado Facturacion | S55: Cali | T55: 25769 | U55: SELLADOR ADHESIVO PU 50 BLANCO 600 ML SA | X55: 2 | Y55: 0 | Z55: 0 | AA55: 0 | AB55: 304800 | AC55: FINALIZADO | AD55: =+VLOOKUP(T55,items!$A$2:$D$1255,4,0) -> 0 | AE55: =+VLOOKUP(T55,Tabla1[],5,0) -> 0 | AF55: =+MONTH(O55) -> 5
A56: 84660 | B56: PETRONIO PéREZ ÁLVAREZ | C56: CUBRIMIENTO | D56: 0 | F56: 2023-08-15 | G56: 2024-05-23 | H56: 2024-05-24 09:27:31 | I56: 0000-00-00 00:00:00 | J56: 2024-05-26 23:35:29 | K56: 2024-05-27 16:13:26 | L56: 0000-00-00 00:00:00 | M56: 2024-05-27 | N56: 2024-05-27 | O56: 2024-05-28 | P56: 2024-05-31 | Q56: 2024-05-31 | R56: Aprobado Facturacion | S56: Cali | T56: REP035 | U56: REPARACION PERGOLA MAT PRIMA | X56: 1 | Y56: 0 | Z56: 0 | AA56: 0 | AB56: 650000 | AC56: FINALIZADO | AD56: =+VLOOKUP(T56,items!$A$2:$D$1255,4,0) -> 0 | AE56: =+VLOOKUP(T56,Tabla1[],5,0) -> 0 | AF56: =+MONTH(O56) -> 5
A57: 85170 | B57: PALVAL 33 DC SAS | C57: MUEBLES CC CUBRIMIENTOS | D57: 0 | F57: 2023-08-18 | G57: 2025-01-29 | H57: 2025-01-30 11:09:55 | I57: 0000-00-00 00:00:00 | J57: 2025-02-16 20:31:22 | K57: 2025-02-18 14:18:38 | L57: 2025-04-23 08:16:22 | M57: 2025-01-31 | N57: 2025-01-31 | O57: 2025-02-24 | P57: 2025-02-26 | Q57: 2025-02-28 | R57: Aprobado Instalación | S57: Virtual | T57: 13672 | U57: ASOLEADORA VICHADA (TA) | V57: FURNISCREEN BEIGE 2M EB4027W G8 625GR | X57: 3 | Y57: 0 | Z57: 0 | AA57: 0 | AB57: 4819524 | AC57: FINALIZADO | AD57: =+VLOOKUP(T57,items!$A$2:$D$1255,4,0) -> MUEBLES | AE57: =+VLOOKUP(T57,Tabla1[],5,0) -> 0 | AF57: =+MONTH(O57) -> 2
A58: 85170 | B58: PALVAL 33 DC SAS | C58: MUEBLES CC CUBRIMIENTOS | D58: 0 | F58: 2023-08-18 | G58: 2025-01-29 | H58: 2025-01-30 11:09:55 | I58: 0000-00-00 00:00:00 | J58: 2025-02-16 20:31:22 | K58: 2025-02-18 14:18:38 | L58: 2025-04-23 08:16:22 | M58: 2025-01-31 | N58: 2025-01-31 | O58: 2025-02-24 | P58: 2025-02-26 | Q58: 2025-02-28 | R58: Aprobado Instalación | S58: Virtual | T58: TRANSP07 | U58: TRANSPORTE FUERA DE CALI MUEBLES | X58: 1 | Y58: 0 | Z58: 0 | AA58: 0 | AB58: 600000 | AC58: FINALIZADO | AD58: =+VLOOKUP(T58,items!$A$2:$D$1255,4,0) -> 0 | AE58: =+VLOOKUP(T58,Tabla1[],5,0) -> 0 | AF58: =+MONTH(O58) -> 2
A59: 86569 | B59: UNIVERSIDAD DEL NORTE | C59: MUEBLES CC CUBRIMIENTOS | D59: 0 | F59: 2023-09-22 | G59: 2024-05-20 | H59: 2024-05-21 13:26:42 | I59: 2024-05-27 16:56:49 | J59: 2024-06-26 09:46:26 | K59: 2024-07-02 08:39:04 | L59: 2024-12-03 10:45:04 | M59: 2024-05-22 | N59: 2024-05-28 | O59: 2024-06-27 | P59: 2024-07-17 | Q59: 2024-12-18 | R59: Aprobado Facturacion | S59: Barranquilla | T59: REP029 | U59: REPARACION MEMBRANA MANO OBRA | X59: 1 | Y59: 0 | Z59: 0 | AA59: 0 | AB59: 2500000 | AC59: FINALIZADO | AD59: =+VLOOKUP(T59,items!$A$2:$D$1255,4,0) -> 0 | AE59: =+VLOOKUP(T59,Tabla1[],5,0) -> 0 | AF59: =+MONTH(O59) -> 6
A60: 86569 | B60: UNIVERSIDAD DEL NORTE | C60: MUEBLES CC CUBRIMIENTOS | D60: 0 | F60: 2023-09-22 | G60: 2024-05-20 | H60: 2024-05-21 13:26:42 | I60: 2024-05-27 16:56:49 | J60: 2024-06-26 09:46:26 | K60: 2024-07-02 08:39:04 | L60: 2024-12-03 10:45:04 | M60: 2024-05-22 | N60: 2024-05-28 | O60: 2024-06-27 | P60: 2024-07-17 | Q60: 2024-12-18 | R60: Aprobado Facturacion | S60: Barranquilla | T60: REP030 | U60: REPARACION MEMBRANA MAT PRIMA | X60: 1 | Y60: 0 | Z60: 0 | AA60: 0 | AB60: 22896543 | AC60: FINALIZADO | AD60: =+VLOOKUP(T60,items!$A$2:$D$1255,4,0) -> 0 | AE60: =+VLOOKUP(T60,Tabla1[],5,0) -> 0 | AF60: =+MONTH(O60) -> 6
A61: 86569 | B61: UNIVERSIDAD DEL NORTE | C61: MUEBLES CC CUBRIMIENTOS | D61: 0 | F61: 2023-09-22 | G61: 2024-05-20 | H61: 2024-05-21 13:26:42 | I61: 2024-05-27 16:56:49 | J61: 2024-06-26 09:46:26 | K61: 2024-07-02 08:39:04 | L61: 2024-12-03 10:45:04 | M61: 2024-05-22 | N61: 2024-05-28 | O61: 2024-06-27 | P61: 2024-07-17 | Q61: 2024-12-18 | R61: Aprobado Facturacion | S61: Barranquilla | T61: SERV03 | U61: SERVICIO VIATICOSINSTALACION CUBRIMIENT | X61: 1 | Y61: 0 | Z61: 0 | AA61: 0 | AB61: 1500000 | AC61: FINALIZADO | AD61: =+VLOOKUP(T61,items!$A$2:$D$1255,4,0) -> #N/A | AE61: =+VLOOKUP(T61,Tabla1[],5,0) -> #N/A | AF61: =+MONTH(O61) -> 6
A62: 86569 | B62: UNIVERSIDAD DEL NORTE | C62: MUEBLES CC CUBRIMIENTOS | D62: 0 | F62: 2023-09-22 | G62: 2024-05-20 | H62: 2024-05-21 13:26:42 | I62: 2024-05-27 16:56:49 | J62: 2024-06-26 09:46:26 | K62: 2024-07-02 08:39:04 | L62: 2024-12-03 10:45:04 | M62: 2024-05-22 | N62: 2024-05-28 | O62: 2024-06-27 | P62: 2024-07-17 | Q62: 2024-12-18 | R62: Aprobado Facturacion | S62: Barranquilla | T62: SERV04 | U62: SERVICIO SISO | X62: 4 | Y62: 0 | Z62: 0 | AA62: 0 | AB62: 480000 | AC62: FINALIZADO | AD62: =+VLOOKUP(T62,items!$A$2:$D$1255,4,0) -> #N/A | AE62: =+VLOOKUP(T62,Tabla1[],5,0) -> #N/A | AF62: =+MONTH(O62) -> 6
A63: 86834 | B63: club colombia | C63: CUBRIMIENTO | D63: 0 | F63: 2023-09-29 | G63: 2024-10-31 | H63: 2024-11-27 10:53:47 | I63: 2024-12-12 18:36:47 | J63: 2024-12-26 13:43:17 | K63: 2024-12-26 15:32:36 | L63: 2025-01-28 13:28:43 | M63: 2024-11-27 | N63: 2024-12-10 | O63: 2024-12-22 | P63: 2024-12-24 | Q63: 2025-01-05 | R63: Facturacion | S63: Gerencia | T63: FLANCHE01 | U63: FLANCHE NACIONAL GALVANIZADO | W63: Negro Señales - RAL 9004 | X63: 1 | Y63: 8000 | Z63: 0 | AA63: 0 | AB63: 0 | AC63: FINALIZADO | AD63: =+VLOOKUP(T63,items!$A$2:$D$1255,4,0) -> 0 | AE63: =+VLOOKUP(T63,Tabla1[],5,0) -> 0 | AF63: =+MONTH(O63) -> 12
A64: 86834 | B64: club colombia | C64: CUBRIMIENTO | D64: 0 | F64: 2023-09-29 | G64: 2024-10-31 | H64: 2024-11-27 10:53:47 | I64: 2024-12-12 18:36:47 | J64: 2024-12-26 13:43:17 | K64: 2024-12-26 15:32:36 | L64: 2025-01-28 13:28:43 | M64: 2024-11-27 | N64: 2024-12-10 | O64: 2024-12-22 | P64: 2024-12-24 | Q64: 2025-01-05 | R64: Facturacion | S64: Gerencia | T64: PLT45 | U64: PLATINA ANCLAJE POSTEMURO PERF.127x127 | W64: Negro Señales - RAL 9004 | X64: 4 | Y64: 0 | Z64: 0 | AA64: 0 | AB64: 982800 | AC64: FINALIZADO | AD64: =+VLOOKUP(T64,items!$A$2:$D$1255,4,0) -> 0 | AE64: =+VLOOKUP(T64,Tabla1[],5,0) -> 0 | AF64: =+MONTH(O64) -> 12
A65: 86834 | B65: club colombia | C65: CUBRIMIENTO | D65: 0 | F65: 2023-09-29 | G65: 2024-10-31 | H65: 2024-11-27 10:53:47 | I65: 2024-12-12 18:36:47 | J65: 2024-12-26 13:43:17 | K65: 2024-12-26 15:32:36 | L65: 2025-01-28 13:28:43 | M65: 2024-11-27 | N65: 2024-12-10 | O65: 2024-12-22 | P65: 2024-12-24 | Q65: 2025-01-05 | R65: Facturacion | S65: Gerencia | T65: PTEKROM02 | U65: PERGOTEK ROMANO MEGA MUROS | V65: LONA PERGOTEX BLACKOUT BLANCA 3 M | W65: Aluminio Anodizado | X65: 1 | Y65: 8000 | Z65: 0 | AA65: 11550 | AB65: 100662251 | AC65: FINALIZADO | AD65: =+VLOOKUP(T65,items!$A$2:$D$1255,4,0) -> PERGOLA | AE65: =+VLOOKUP(T65,Tabla1[],5,0) -> PERGOTEK ROMANO | AF65: =+MONTH(O65) -> 12
A66: 86834 | B66: club colombia | C66: CUBRIMIENTO | D66: 0 | F66: 2023-09-29 | G66: 2024-10-31 | H66: 2024-11-27 10:53:47 | I66: 2024-12-12 18:36:47 | J66: 2024-12-26 13:43:17 | K66: 2024-12-26 15:32:36 | L66: 2025-01-28 13:28:43 | M66: 2024-11-27 | N66: 2024-12-10 | O66: 2024-12-22 | P66: 2024-12-24 | Q66: 2025-01-05 | R66: Facturacion | S66: Gerencia | T66: SERV03 | U66: SERVICIO VIATICOSINSTALACION CUBRIMIENT | X66: 1 | Y66: 0 | Z66: 0 | AA66: 0 | AB66: 1578947 | AC66: FINALIZADO | AD66: =+VLOOKUP(T66,items!$A$2:$D$1255,4,0) -> #N/A | AE66: =+VLOOKUP(T66,Tabla1[],5,0) -> #N/A | AF66: =+MONTH(O66) -> 12
A67: 86834 | B67: club colombia | C67: CUBRIMIENTO | D67: 0 | F67: 2023-09-29 | G67: 2024-10-31 | H67: 2024-11-27 10:53:47 | I67: 2024-12-12 18:36:47 | J67: 2024-12-26 13:43:17 | K67: 2024-12-26 15:32:36 | L67: 2025-01-28 13:28:43 | M67: 2024-11-27 | N67: 2024-12-10 | O67: 2024-12-22 | P67: 2024-12-24 | Q67: 2025-01-05 | R67: Facturacion | S67: Gerencia | T67: SPOT30 | U67: SISTEMA ELECTRICO 30 SPOT PARA PERGOLA | X67: 1 | Y67: 0 | Z67: 0 | AA67: 0 | AB67: 0 | AC67: FINALIZADO | AD67: =+VLOOKUP(T67,items!$A$2:$D$1255,4,0) -> 0 | AE67: =+VLOOKUP(T67,Tabla1[],5,0) -> 0 | AF67: =+MONTH(O67) -> 12
A68: 86862 | B68: Arte Patio | C68: CUBRIMIENTO | D68: 0 | F68: 2023-10-02 | G68: 2024-06-14 | H68: 2024-07-19 16:30:54 | I68: 2024-07-19 16:30:59 | J68: 2024-07-19 16:31:04 | K68: 2024-08-02 17:53:26 | L68: 2024-10-16 07:12:00 | M68: 2024-06-18 | N68: 2024-06-28 | O68: 2024-07-12 | P68: 2024-07-16 | Q68: 2024-07-25 | R68: Aprobado Instalación | S68: Toscana | T68: PLAM08 | U68: MAXI PERGOLAM GAZEBO | W68: Blanco Señal - RAL 9003 | X68: 2 | Y68: 3000 | Z68: 0 | AA68: 5943 | AB68: 90887198 | AC68: FINALIZADO | AD68: =+VLOOKUP(T68,items!$A$2:$D$1255,4,0) -> PERGOLA | AE68: =+VLOOKUP(T68,Tabla1[],5,0) -> MAXI PERGOLAM | AF68: =+MONTH(O68) -> 7 | AG68: 3816 | AH68: 90887198
A69: 87114 | B69: Maria Cristina Ruiz | C69: MUEBLES CC CUBRIMIENTOS | D69: 0 | F69: 2023-10-06 | G69: 2025-10-02 | H69: 2025-10-14 14:29:55 | I69: 0000-00-00 00:00:00 | J69: 2025-11-03 21:00:03 | K69: 2025-11-04 08:10:06 | L69: 0000-00-00 00:00:00 | M69: 2025-10-14 | N69: 2025-10-14 | O69: 2025-11-17 | P69: 2025-11-21 | Q69: 2025-11-22 | R69: Aprobado Despachos | S69: Virtual | T69: 9683 | U69: MALLA SILLA VENUS | X69: 6 | Y69: 0 | Z69: 0 | AA69: 0 | AB69: 972000 | AC69: FINALIZADO | AD69: =+VLOOKUP(T69,items!$A$2:$D$1255,4,0) -> 0 | AE69: =+VLOOKUP(T69,Tabla1[],5,0) -> 0 | AF69: =+MONTH(O69) -> 11
A70: 87114 | B70: Maria Cristina Ruiz | C70: MUEBLES CC CUBRIMIENTOS | D70: 0 | F70: 2023-10-06 | G70: 2025-10-02 | H70: 2025-10-14 14:29:55 | I70: 0000-00-00 00:00:00 | J70: 2025-11-03 21:00:03 | K70: 2025-11-04 08:10:06 | L70: 0000-00-00 00:00:00 | M70: 2025-10-14 | N70: 2025-10-14 | O70: 2025-11-17 | P70: 2025-11-21 | Q70: 2025-11-22 | R70: Aprobado Despachos | S70: Virtual | T70: REP040 | U70: REPARACION SILLA MAT PRIMA | X70: 6 | Y70: 0 | Z70: 0 | AA70: 0 | AB70: 2570400 | AC70: FINALIZADO | AD70: =+VLOOKUP(T70,items!$A$2:$D$1255,4,0) -> 0 | AE70: =+VLOOKUP(T70,Tabla1[],5,0) -> 0 | AF70: =+MONTH(O70) -> 11
A71: 87114 | B71: Maria Cristina Ruiz | C71: MUEBLES CC CUBRIMIENTOS | D71: 0 | F71: 2023-10-06 | G71: 2025-10-02 | H71: 2025-10-14 14:29:55 | I71: 0000-00-00 00:00:00 | J71: 2025-11-03 21:00:03 | K71: 2025-11-04 08:10:06 | L71: 0000-00-00 00:00:00 | M71: 2025-10-14 | N71: 2025-10-14 | O71: 2025-11-17 | P71: 2025-11-21 | Q71: 2025-11-22 | R71: Aprobado Despachos | S71: Virtual | T71: TRANSP07 | U71: TRANSPORTE FUERA DE CALI MUEBLES | X71: 1 | Y71: 0 | Z71: 0 | AA71: 0 | AB71: 480000 | AC71: FINALIZADO | AD71: =+VLOOKUP(T71,items!$A$2:$D$1255,4,0) -> 0 | AE71: =+VLOOKUP(T71,Tabla1[],5,0) -> 0 | AF71: =+MONTH(O71) -> 11
A72: 89387 | B72: BLUE DOORS YORK LUXURY SUITES S.A.S | C72: CUBRIMIENTO | D72: 0 | F72: 2023-12-19 | G72: 2024-11-30 | H72: 2024-12-10 11:43:30 | I72: 0000-00-00 00:00:00 | J72: 2024-12-16 07:51:33 | K72: 2024-12-16 07:52:18 | L72: 2025-01-22 13:21:06 | M72: 2024-12-10 | N72: 2024-12-10 | O72: 2024-12-12 | P72: 2024-12-18 | Q72: 2024-12-20 | R72: Aprobado Instalación | S72: medellin | T72: 3151 | U72: CORREA DENTADA 19mm PERGOLAS RETRACTILES | X72: 23 | Y72: 0 | Z72: 0 | AA72: 0 | AB72: 1638750 | AC72: FINALIZADO | AD72: =+VLOOKUP(T72,items!$A$2:$D$1255,4,0) -> 0 | AE72: =+VLOOKUP(T72,Tabla1[],5,0) -> 0 | AF72: =+MONTH(O72) -> 12
A73: 89387 | B73: BLUE DOORS YORK LUXURY SUITES S.A.S | C73: CUBRIMIENTO | D73: 0 | F73: 2023-12-19 | G73: 2024-11-30 | H73: 2024-12-10 11:43:30 | I73: 0000-00-00 00:00:00 | J73: 2024-12-16 07:51:33 | K73: 2024-12-16 07:52:18 | L73: 2025-01-22 13:21:06 | M73: 2024-12-10 | N73: 2024-12-10 | O73: 2024-12-12 | P73: 2024-12-18 | Q73: 2024-12-20 | R73: Aprobado Instalación | S73: medellin | T73: SERV03 | U73: SERVICIO VIATICOSINSTALACION CUBRIMIENT | X73: 1 | Y73: 0 | Z73: 0 | AA73: 0 | AB73: 450000 | AC73: FINALIZADO | AD73: =+VLOOKUP(T73,items!$A$2:$D$1255,4,0) -> #N/A | AE73: =+VLOOKUP(T73,Tabla1[],5,0) -> #N/A | AF73: =+MONTH(O73) -> 12
A74: 89387 | B74: BLUE DOORS YORK LUXURY SUITES S.A.S | C74: CUBRIMIENTO | D74: 0 | F74: 2023-12-19 | G74: 2024-11-30 | H74: 2024-12-10 11:43:30 | I74: 0000-00-00 00:00:00 | J74: 2024-12-16 07:51:33 | K74: 2024-12-16 07:52:18 | L74: 2025-01-22 13:21:06 | M74: 2024-12-10 | N74: 2024-12-10 | O74: 2024-12-12 | P74: 2024-12-18 | Q74: 2024-12-20 | R74: Aprobado Instalación | S74: medellin | T74: SERV03 | U74: SERVICIO VIATICOSINSTALACION CUBRIMIENT | X74: 1 | Y74: 0 | Z74: 0 | AA74: 0 | AB74: 480000 | AC74: FINALIZADO | AD74: =+VLOOKUP(T74,items!$A$2:$D$1255,4,0) -> #N/A | AE74: =+VLOOKUP(T74,Tabla1[],5,0) -> #N/A | AF74: =+MONTH(O74) -> 12
A75: 89387 | B75: BLUE DOORS YORK LUXURY SUITES S.A.S | C75: CUBRIMIENTO | D75: 0 | F75: 2023-12-19 | G75: 2024-11-30 | H75: 2024-12-10 11:43:30 | I75: 0000-00-00 00:00:00 | J75: 2024-12-16 07:51:33 | K75: 2024-12-16 07:52:18 | L75: 2025-01-22 13:21:06 | M75: 2024-12-10 | N75: 2024-12-10 | O75: 2024-12-12 | P75: 2024-12-18 | Q75: 2024-12-20 | R75: Aprobado Instalación | S75: medellin | T75: SERVLAV04 | U75: SERVICIO MTTO LAVADO PERGOTEK | X75: 1 | Y75: 0 | Z75: 0 | AA75: 0 | AB75: 890000 | AC75: FINALIZADO | AD75: =+VLOOKUP(T75,items!$A$2:$D$1255,4,0) -> #N/A | AE75: =+VLOOKUP(T75,Tabla1[],5,0) -> #N/A | AF75: =+MONTH(O75) -> 12
A76: 89387 | B76: BLUE DOORS YORK LUXURY SUITES S.A.S | C76: CUBRIMIENTO | D76: 0 | F76: 2023-12-19 | G76: 2024-11-30 | H76: 2024-12-10 11:43:30 | I76: 0000-00-00 00:00:00 | J76: 2024-12-16 07:51:33 | K76: 2024-12-16 07:52:18 | L76: 2025-01-22 13:21:06 | M76: 2024-12-10 | N76: 2024-12-10 | O76: 2024-12-12 | P76: 2024-12-18 | Q76: 2024-12-20 | R76: Aprobado Instalación | S76: medellin | T76: SERVLAV04 | U76: SERVICIO MTTO LAVADO PERGOTEK | X76: 1 | Y76: 0 | Z76: 0 | AA76: 0 | AB76: 890000 | AC76: FINALIZADO | AD76: =+VLOOKUP(T76,items!$A$2:$D$1255,4,0) -> #N/A | AE76: =+VLOOKUP(T76,Tabla1[],5,0) -> #N/A | AF76: =+MONTH(O76) -> 12
A77: 89387 | B77: BLUE DOORS YORK LUXURY SUITES S.A.S | C77: CUBRIMIENTO | D77: 0 | F77: 2023-12-19 | G77: 2024-11-30 | H77: 2024-12-10 11:43:30 | I77: 0000-00-00 00:00:00 | J77: 2024-12-16 07:51:33 | K77: 2024-12-16 07:52:18 | L77: 2025-01-22 13:21:06 | M77: 2024-12-10 | N77: 2024-12-10 | O77: 2024-12-12 | P77: 2024-12-18 | Q77: 2024-12-20 | R77: Aprobado Instalación | S77: medellin | T77: TRANSP06 | U77: SERVICIO TRANSPORTE CUBRIMIENTOS | X77: 1 | Y77: 0 | Z77: 0 | AA77: 0 | AB77: 160000 | AC77: FINALIZADO | AD77: =+VLOOKUP(T77,items!$A$2:$D$1255,4,0) -> #N/A | AE77: =+VLOOKUP(T77,Tabla1[],5,0) -> #N/A | AF77: =+MONTH(O77) -> 12
A78: 89837 | B78: AMORE GROUP | C78: CUBRIMIENTO | D78: 0 | F78: 2024-01-12 | G78: 2024-05-20 | H78: 2024-05-27 10:36:41 | I78: 0000-00-00 00:00:00 | J78: 2024-05-31 10:55:57 | K78: 2024-06-11 11:19:29 | L78: 0000-00-00 00:00:00 | M78: 2024-05-27 | N78: 2024-05-27 | O78: 2024-06-10 | P78: 2024-06-15 | Q78: 2024-06-18 | R78: Aprobado Despachos | S78: Cali | T78: REP007 | U78: REPARACION BANETA GUILLO MAT PRIMA | X78: 1 | Y78: 0 | Z78: 0 | AA78: 0 | AB78: 512000 | AC78: FINALIZADO | AD78: =+VLOOKUP(T78,items!$A$2:$D$1255,4,0) -> 0 | AE78: =+VLOOKUP(T78,Tabla1[],5,0) -> 0 | AF78: =+MONTH(O78) -> 6
A79: 89837 | B79: AMORE GROUP | C79: CUBRIMIENTO | D79: 0 | F79: 2024-01-12 | G79: 2024-05-20 | H79: 2024-05-27 10:36:41 | I79: 0000-00-00 00:00:00 | J79: 2024-05-31 10:55:57 | K79: 2024-06-11 11:19:29 | L79: 0000-00-00 00:00:00 | M79: 2024-05-27 | N79: 2024-05-27 | O79: 2024-06-10 | P79: 2024-06-15 | Q79: 2024-06-18 | R79: Aprobado Despachos | S79: Cali | T79: REP007 | U79: REPARACION BANETA GUILLO MAT PRIMA | X79: 1 | Y79: 0 | Z79: 0 | AA79: 0 | AB79: 192000 | AC79: FINALIZADO | AD79: =+VLOOKUP(T79,items!$A$2:$D$1255,4,0) -> 0 | AE79: =+VLOOKUP(T79,Tabla1[],5,0) -> 0 | AF79: =+MONTH(O79) -> 6
A80: 89837 | B80: AMORE GROUP | C80: CUBRIMIENTO | D80: 0 | F80: 2024-01-12 | G80: 2024-05-20 | H80: 2024-05-27 10:36:41 | I80: 0000-00-00 00:00:00 | J80: 2024-05-31 10:55:57 | K80: 2024-06-11 11:19:29 | L80: 0000-00-00 00:00:00 | M80: 2024-05-27 | N80: 2024-05-27 | O80: 2024-06-10 | P80: 2024-06-15 | Q80: 2024-06-18 | R80: Aprobado Despachos | S80: Cali | T80: REP007 | U80: REPARACION BANETA GUILLO MAT PRIMA | X80: 1 | Y80: 0 | Z80: 0 | AA80: 0 | AB80: 448000 | AC80: FINALIZADO | AD80: =+VLOOKUP(T80,items!$A$2:$D$1255,4,0) -> 0 | AE80: =+VLOOKUP(T80,Tabla1[],5,0) -> 0 | AF80: =+MONTH(O80) -> 6
... A92: 89976 | B92: A&C INMOBILIARIOS SAS | C92: CUBRIMIENTO | D92: 0 | F92: 0000-00-00 | G92: 2024-08-08 | H92: 2024-08-13 17:10:01 | I92: 2024-10-08 10:10:42 | J92: 2024-10-25 14:37:34 | K92: 2024-12-19 18:39:01 | L92: 2025-09-17 09:44:03 | M92: 2024-08-16 | N92: 2024-10-11 | O92: 2024-10-28 | P92: 2024-11-12 | Q92: 2024-12-02 | R92: Aprobado Instalación | S92: Cali | T92: CANAL GALVANIZ PTEK | U92: CANAL GALVANIZADA PERGOTEK | X92: 1 | Y92: 11700 | Z92: 0 | AA92: 0 | AB92: 7568946 | AC92: FINALIZADO | AD92: =+VLOOKUP(T92,items!$A$2:$D$1255,4,0) -> 0 | AE92: =+VLOOKUP(T92,Tabla1[],5,0) -> 0 | AF92: =+MONTH(O92) -> 10
A93: 89976 | B93: A&C INMOBILIARIOS SAS | C93: CUBRIMIENTO | D93: 0 | F93: 0000-00-00 | G93: 2024-08-08 | H93: 2024-08-13 17:10:01 | I93: 2024-10-08 10:10:42 | J93: 2024-10-25 14:37:34 | K93: 2024-12-19 18:39:01 | L93: 2025-09-17 09:44:03 | M93: 2024-08-16 | N93: 2024-10-11 | O93: 2024-10-28 | P93: 2024-11-12 | Q93: 2024-12-02 | R93: Aprobado Instalación | S93: Cali | T93: CUBT03 | U93: CUBIERTA EN POLICARBONATO | W93: Negro Señales - RAL 9004 | X93: 1 | Y93: 12000 | Z93: 0 | AA93: 3500 | AB93: 12154534 | AC93: FINALIZADO | AD93: =+VLOOKUP(T93,items!$A$2:$D$1255,4,0) -> 0 | AE93: =+VLOOKUP(T93,Tabla1[],5,0) -> 0 | AF93: =+MONTH(O93) -> 10
A94: 89976 | B94: A&C INMOBILIARIOS SAS | C94: CUBRIMIENTO | D94: 0 | F94: 0000-00-00 | G94: 2024-08-08 | H94: 2024-08-13 17:10:01 | I94: 2024-10-08 10:10:42 | J94: 2024-10-25 14:37:34 | K94: 2024-12-19 18:39:01 | L94: 2025-09-17 09:44:03 | M94: 2024-08-16 | N94: 2024-10-11 | O94: 2024-10-28 | P94: 2024-11-12 | Q94: 2024-12-02 | R94: Aprobado Instalación | S94: Cali | T94: CUBT03 | U94: CUBIERTA EN POLICARBONATO | W94: Negro Señales - RAL 9004 | X94: 1 | Y94: 3500 | Z94: 0 | AA94: 2500 | AB94: 2532194 | AC94: FINALIZADO | AD94: =+VLOOKUP(T94,items!$A$2:$D$1255,4,0) -> 0 | AE94: =+VLOOKUP(T94,Tabla1[],5,0) -> 0 | AF94: =+MONTH(O94) -> 10
A95: 89976 | B95: A&C INMOBILIARIOS SAS | C95: CUBRIMIENTO | D95: 0 | F95: 0000-00-00 | G95: 2024-08-08 | H95: 2024-08-13 17:10:01 | I95: 2024-10-08 10:10:42 | J95: 2024-10-25 14:37:34 | K95: 2024-12-19 18:39:01 | L95: 2025-09-17 09:44:03 | M95: 2024-08-16 | N95: 2024-10-11 | O95: 2024-10-28 | P95: 2024-11-12 | Q95: 2024-12-02 | R95: Aprobado Instalación | S95: Cali | T95: PFLT05 | U95: PERGOLA FIJA ALUTECA GRANDE | W95: Negro Señales - RAL 9004 | X95: 1 | Y95: 11700 | Z95: 0 | AA95: 3500 | AB95: 40424433 | AC95: FINALIZADO | AD95: =+VLOOKUP(T95,items!$A$2:$D$1255,4,0) -> PERGOLA | AE95: =+VLOOKUP(T95,Tabla1[],5,0) -> PERGOLA FIJA | AF95: =+MONTH(O95) -> 10
A96: 89976 | B96: A&C INMOBILIARIOS SAS | C96: CUBRIMIENTO | D96: 0 | F96: 0000-00-00 | G96: 2024-08-08 | H96: 2024-08-13 17:10:01 | I96: 2024-10-08 10:10:42 | J96: 2024-10-25 14:37:34 | K96: 2024-12-19 18:39:01 | L96: 2025-09-17 09:44:03 | M96: 2024-08-16 | N96: 2024-10-11 | O96: 2024-10-28 | P96: 2024-11-12 | Q96: 2024-12-02 | R96: Aprobado Instalación | S96: Cali | T96: PTAC03 | U96: POSTE ACERO 120x120 | W96: Negro Señales - RAL 9004 | X96: 3 | Y96: 0 | Z96: 4000 | AA96: 0 | AB96: 5874231 | AC96: FINALIZADO | AD96: =+VLOOKUP(T96,items!$A$2:$D$1255,4,0) -> 0 | AE96: =+VLOOKUP(T96,Tabla1[],5,0) -> 0 | AF96: =+MONTH(O96) -> 10
A97: 89976 | B97: A&C INMOBILIARIOS SAS | C97: CUBRIMIENTO | D97: 0 | F97: 0000-00-00 | G97: 2024-08-08 | H97: 2024-08-13 17:10:01 | I97: 2024-10-08 10:10:42 | J97: 2024-10-25 14:37:34 | K97: 2024-12-19 18:39:01 | L97: 2025-09-17 09:44:03 | M97: 2024-08-16 | N97: 2024-10-11 | O97: 2024-10-28 | P97: 2024-11-12 | Q97: 2024-12-02 | R97: Aprobado Instalación | S97: Cali | T97: SERV03 | U97: SERVICIO VIATICOSINSTALACION CUBRIMIENT | X97: 1 | Y97: 0 | Z97: 0 | AA97: 0 | AB97: 1785000 | AC97: FINALIZADO | AD97: =+VLOOKUP(T97,items!$A$2:$D$1255,4,0) -> #N/A | AE97: =+VLOOKUP(T97,Tabla1[],5,0) -> #N/A | AF97: =+MONTH(O97) -> 10
A98: 89976 | B98: A&C INMOBILIARIOS SAS | C98: CUBRIMIENTO | D98: 0 | F98: 0000-00-00 | G98: 2024-08-08 | H98: 2024-08-13 17:10:01 | I98: 2024-10-08 10:10:42 | J98: 2024-10-25 14:37:34 | K98: 2024-12-19 18:39:01 | L98: 2025-09-17 09:44:03 | M98: 2024-08-16 | N98: 2024-10-11 | O98: 2024-10-28 | P98: 2024-11-12 | Q98: 2024-12-02 | R98: Aprobado Instalación | S98: Cali | T98: SOLAPA01 | U98: PERFIL SOLAPA | W98: Negro Señales - RAL 9004 | X98: 1 | Y98: 17000 | Z98: 0 | AA98: 0 | AB98: 578488 | AC98: FINALIZADO | AD98: =+VLOOKUP(T98,items!$A$2:$D$1255,4,0) -> 0 | AE98: =+VLOOKUP(T98,Tabla1[],5,0) -> 0 | AF98: =+MONTH(O98) -> 10
A99: 89976 | B99: A&C INMOBILIARIOS SAS | C99: CUBRIMIENTO | D99: 0 | F99: 0000-00-00 | G99: 2024-08-08 | H99: 2024-08-13 17:10:01 | I99: 2024-10-08 10:10:42 | J99: 2024-10-25 14:37:34 | K99: 2024-12-19 18:39:01 | L99: 2025-09-17 09:44:03 | M99: 2024-08-16 | N99: 2024-10-11 | O99: 2024-10-28 | P99: 2024-11-12 | Q99: 2024-12-02 | R99: Aprobado Instalación | S99: Cali | T99: SPOT26 | U99: SISTEMA ELECTRICO 26 SPOT PARA PERGOLA | X99: 1 | Y99: 0 | Z99: 0 | AA99: 0 | AB99: 4043076 | AC99: FINALIZADO | AD99: =+VLOOKUP(T99,items!$A$2:$D$1255,4,0) -> 0 | AE99: =+VLOOKUP(T99,Tabla1[],5,0) -> 0 | AF99: =+MONTH(O99) -> 10
A100: 90224 | B100: PATRIMONIOS AUTONOMOS FIDUCIARIA COOMEVA S.A | C100: CUBRIMIENTO | D100: 0 | F100: 2024-01-24 | G100: 2024-11-28 | H100: 2024-12-02 10:34:15 | I100: 0000-00-00 00:00:00 | J100: 2024-12-03 14:36:03 | K100: 2025-01-08 07:32:54 | L100: 0000-00-00 00:00:00 | M100: 2024-12-02 | N100: 2024-12-02 | O100: 2024-12-03 | P100: 2024-12-23 | Q100: 2024-12-28 | R100: Aprobado Facturacion | S100: Bogota | T100: SERVLAV04 | U100: SERVICIO MTTO LAVADO PERGOTEK | X100: 1 | Y100: 0 | Z100: 0 | AA100: 0 | AB100: 1305000 | AC100: FINALIZADO | AD100: =+VLOOKUP(T100,items!$A$2:$D$1255,4,0) -> #N/A | AE100: =+VLOOKUP(T100,Tabla1[],5,0) -> #N/A | AF100: =+MONTH(O100) -> 12
A101: 90224 | B101: PATRIMONIOS AUTONOMOS FIDUCIARIA COOMEVA S.A | C101: CUBRIMIENTO | D101: 0 | F101: 2024-01-24 | G101: 2024-11-28 | H101: 2024-12-02 10:34:15 | I101: 0000-00-00 00:00:00 | J101: 2024-12-03 14:36:03 | K101: 2025-01-08 07:32:54 | L101: 0000-00-00 00:00:00 | M101: 2024-12-02 | N101: 2024-12-02 | O101: 2024-12-03 | P101: 2024-12-23 | Q101: 2024-12-28 | R101: Aprobado Facturacion | S101: Bogota | T101: SERVLAV04 | U101: SERVICIO MTTO LAVADO PERGOTEK | X101: 1 | Y101: 0 | Z101: 0 | AA101: 0 | AB101: 2880360 | AC101: FINALIZADO | AD101: =+VLOOKUP(T101,items!$A$2:$D$1255,4,0) -> #N/A | AE101: =+VLOOKUP(T101,Tabla1[],5,0) -> #N/A | AF101: =+MONTH(O101) -> 12
A102: 90224 | B102: PATRIMONIOS AUTONOMOS FIDUCIARIA COOMEVA S.A | C102: CUBRIMIENTO | D102: 0 | F102: 2024-01-24 | G102: 2024-11-28 | H102: 2024-12-02 10:34:15 | I102: 0000-00-00 00:00:00 | J102: 2024-12-03 14:36:03 | K102: 2025-01-08 07:32:54 | L102: 0000-00-00 00:00:00 | M102: 2024-12-02 | N102: 2024-12-02 | O102: 2024-12-03 | P102: 2024-12-23 | Q102: 2024-12-28 | R102: Aprobado Facturacion | S102: Bogota | T102: SERVLAV04 | U102: SERVICIO MTTO LAVADO PERGOTEK | X102: 1 | Y102: 0 | Z102: 0 | AA102: 0 | AB102: 1559250 | AC102: FINALIZADO | AD102: =+VLOOKUP(T102,items!$A$2:$D$1255,4,0) -> #N/A | AE102: =+VLOOKUP(T102,Tabla1[],5,0) -> #N/A | AF102: =+MONTH(O102) -> 12
A103: 90224 | B103: PATRIMONIOS AUTONOMOS FIDUCIARIA COOMEVA S.A | C103: CUBRIMIENTO | D103: 0 | F103: 2024-01-24 | G103: 2024-11-28 | H103: 2024-12-02 10:34:15 | I103: 0000-00-00 00:00:00 | J103: 2024-12-03 14:36:03 | K103: 2025-01-08 07:32:54 | L103: 0000-00-00 00:00:00 | M103: 2024-12-02 | N103: 2024-12-02 | O103: 2024-12-03 | P103: 2024-12-23 | Q103: 2024-12-28 | R103: Aprobado Facturacion | S103: Bogota | T103: SERVLAV04 | U103: SERVICIO MTTO LAVADO PERGOTEK | X103: 1 | Y103: 0 | Z103: 0 | AA103: 0 | AB103: 2164770 | AC103: FINALIZADO | AD103: =+VLOOKUP(T103,items!$A$2:$D$1255,4,0) -> #N/A | AE103: =+VLOOKUP(T103,Tabla1[],5,0) -> #N/A | AF103: =+MONTH(O103) -> 12
A104: 90349 | B104: FRISBY S.A. BIC FRISBY S.A. BIC | C104: CUBRIMIENTO | D104: 0 | F104: 2024-01-29 | G104: 2024-05-29 | H104: 2024-06-11 13:57:42 | I104: 2024-06-19 17:39:36 | J104: 2024-07-06 16:12:27 | K104: 2024-07-10 10:33:59 | L104: 2024-07-26 03:34:35 | M104: 2024-06-11 | N104: 2024-06-19 | O104: 2024-07-06 | P104: 2024-07-10 | Q104: 2024-07-20 | R104: Aprobado Facturacion | S104: Cali | T104: FLANCHE01 | U104: FLANCHE NACIONAL GALVANIZADO | W104: Gris Antracita - RAL 7016 | X104: 1 | Y104: 9000 | Z104: 0 | AA104: 0 | AB104: 1158960 | AC104: FINALIZADO | AD104: =+VLOOKUP(T104,items!$A$2:$D$1255,4,0) -> 0 | AE104: =+VLOOKUP(T104,Tabla1[],5,0) -> 0 | AF104: =+MONTH(O104) -> 7
A105: 90349 | B105: FRISBY S.A. BIC FRISBY S.A. BIC | C105: CUBRIMIENTO | D105: 0 | F105: 2024-01-29 | G105: 2024-05-29 | H105: 2024-06-11 13:57:42 | I105: 2024-06-19 17:39:36 | J105: 2024-07-06 16:12:27 | K105: 2024-07-10 10:33:59 | L105: 2024-07-26 03:34:35 | M105: 2024-06-11 | N105: 2024-06-19 | O105: 2024-07-06 | P105: 2024-07-10 | Q105: 2024-07-20 | R105: Aprobado Facturacion | S105: Cali | T105: SERV03 | U105: SERVICIO VIATICOSINSTALACION CUBRIMIENT | X105: 1 | Y105: 0 | Z105: 0 | AA105: 0 | AB105: 1600000 | AC105: FINALIZADO | AD105: =+VLOOKUP(T105,items!$A$2:$D$1255,4,0) -> #N/A | AE105: =+VLOOKUP(T105,Tabla1[],5,0) -> #N/A | AF105: =+MONTH(O105) -> 7
A106: 90349 | B106: FRISBY S.A. BIC FRISBY S.A. BIC | C106: CUBRIMIENTO | D106: 0 | F106: 2024-01-29 | G106: 2024-05-29 | H106: 2024-06-11 13:57:42 | I106: 2024-06-19 17:39:36 | J106: 2024-07-06 16:12:27 | K106: 2024-07-10 10:33:59 | L106: 2024-07-26 03:34:35 | M106: 2024-06-11 | N106: 2024-06-19 | O106: 2024-07-06 | P106: 2024-07-10 | Q106: 2024-07-20 | R106: Aprobado Facturacion | S106: Cali | T106: SOMB01 | U106: SOMBRALINA ELECTRICA | V106: LONA DICKSON CARBONE REF:U-171 | W106: Gris Antracita - RAL 7016 | X106: 1 | Y106: 9000 | Z106: 0 | AA106: 3000 | AB106: 12984573 | AC106: FINALIZADO | AD106: =+VLOOKUP(T106,items!$A$2:$D$1255,4,0) -> SOMBRALINA | AE106: =+VLOOKUP(T106,Tabla1[],5,0) -> ELECTRICA | AF106: =+MONTH(O106) -> 7
A107: 90354 | B107: ATEMPO INVERSIONES S.A.S. | C107: CUBRIMIENTO | D107: 0 | F107: 2024-01-29 | G107: 2024-06-08 | H107: 2024-06-11 13:46:57 | I107: 0000-00-00 00:00:00 | J107: 2024-06-13 07:27:05 | K107: 2024-06-13 07:27:40 | L107: 0000-00-00 00:00:00 | M107: 2024-06-11 | N107: 2024-06-11 | O107: 2024-06-25 | P107: 2024-06-28 | Q107: 2024-06-28 | R107: Aprobado Despachos | S107: Bogota | T107: 3151 | U107: CORREA DENTADA 19mm PERGOLAS RETRACTILES | X107: 15 | Y107: 0 | Z107: 0 | AA107: 0 | AB107: 1500000 | AC107: FINALIZADO | AD107: =+VLOOKUP(T107,items!$A$2:$D$1255,4,0) -> 0 | AE107: =+VLOOKUP(T107,Tabla1[],5,0) -> 0 | AF107: =+MONTH(O107) -> 6
A108: 90354 | B108: ATEMPO INVERSIONES S.A.S. | C108: CUBRIMIENTO | D108: 0 | F108: 2024-01-29 | G108: 2024-06-08 | H108: 2024-06-11 13:46:57 | I108: 0000-00-00 00:00:00 | J108: 2024-06-13 07:27:05 | K108: 2024-06-13 07:27:40 | L108: 0000-00-00 00:00:00 | M108: 2024-06-11 | N108: 2024-06-11 | O108: 2024-06-25 | P108: 2024-06-28 | Q108: 2024-06-28 | R108: Aprobado Despachos | S108: Bogota | T108: REP036 | U108: REPARACION PERGOLA MANO OBRA | X108: 1 | Y108: 0 | Z108: 0 | AA108: 0 | AB108: 895650 | AC108: FINALIZADO | AD108: =+VLOOKUP(T108,items!$A$2:$D$1255,4,0) -> 0 | AE108: =+VLOOKUP(T108,Tabla1[],5,0) -> 0 | AF108: =+MONTH(O108) -> 6
A109: 90354 | B109: ATEMPO INVERSIONES S.A.S. | C109: CUBRIMIENTO | D109: 0 | F109: 2024-01-29 | G109: 2024-06-08 | H109: 2024-06-11 13:46:57 | I109: 0000-00-00 00:00:00 | J109: 2024-06-13 07:27:05 | K109: 2024-06-13 07:27:40 | L109: 0000-00-00 00:00:00 | M109: 2024-06-11 | N109: 2024-06-11 | O109: 2024-06-25 | P109: 2024-06-28 | Q109: 2024-06-28 | R109: Aprobado Despachos | S109: Bogota | T109: REP036 | U109: REPARACION PERGOLA MANO OBRA | X109: 1 | Y109: 0 | Z109: 0 | AA109: 0 | AB109: 800000 | AC109: FINALIZADO | AD109: =+VLOOKUP(T109,items!$A$2:$D$1255,4,0) -> 0 | AE109: =+VLOOKUP(T109,Tabla1[],5,0) -> 0 | AF109: =+MONTH(O109) -> 6
A110: 90354 | B110: ATEMPO INVERSIONES S.A.S. | C110: CUBRIMIENTO | D110: 0 | F110: 2024-01-29 | G110: 2024-06-08 | H110: 2024-06-11 13:46:57 | I110: 0000-00-00 00:00:00 | J110: 2024-06-13 07:27:05 | K110: 2024-06-13 07:27:40 | L110: 0000-00-00 00:00:00 | M110: 2024-06-11 | N110: 2024-06-11 | O110: 2024-06-25 | P110: 2024-06-28 | Q110: 2024-06-28 | R110: Aprobado Despachos | S110: Bogota | T110: REP036 | U110: REPARACION PERGOLA MANO OBRA | X110: 1 | Y110: 0 | Z110: 0 | AA110: 0 | AB110: 707000 | AC110: FINALIZADO | AD110: =+VLOOKUP(T110,items!$A$2:$D$1255,4,0) -> 0 | AE110: =+VLOOKUP(T110,Tabla1[],5,0) -> 0 | AF110: =+MONTH(O110) -> 6
A111: 90354 | B111: ATEMPO INVERSIONES S.A.S. | C111: CUBRIMIENTO | D111: 0 | F111: 2024-01-29 | G111: 2024-06-08 | H111: 2024-06-11 13:46:57 | I111: 0000-00-00 00:00:00 | J111: 2024-06-13 07:27:05 | K111: 2024-06-13 07:27:40 | L111: 0000-00-00 00:00:00 | M111: 2024-06-11 | N111: 2024-06-11 | O111: 2024-06-25 | P111: 2024-06-28 | Q111: 2024-06-28 | R111: Aprobado Despachos | S111: Bogota | T111: SERVLAV04 | U111: SERVICIO MTTO LAVADO PERGOTEK | X111: 1 | Y111: 0 | Z111: 0 | AA111: 0 | AB111: 808000 | AC111: FINALIZADO | AD111: =+VLOOKUP(T111,items!$A$2:$D$1255,4,0) -> #N/A | AE111: =+VLOOKUP(T111,Tabla1[],5,0) -> #N/A | AF111: =+MONTH(O111) -> 6
A112: 90354 | B112: ATEMPO INVERSIONES S.A.S. | C112: CUBRIMIENTO | D112: 0 | F112: 2024-01-29 | G112: 2024-06-08 | H112: 2024-06-11 13:46:57 | I112: 0000-00-00 00:00:00 | J112: 2024-06-13 07:27:05 | K112: 2024-06-13 07:27:40 | L112: 0000-00-00 00:00:00 | M112: 2024-06-11 | N112: 2024-06-11 | O112: 2024-06-25 | P112: 2024-06-28 | Q112: 2024-06-28 | R112: Aprobado Despachos | S112: Bogota | T112: SERVLAV04 | U112: SERVICIO MTTO LAVADO PERGOTEK | X112: 1 | Y112: 0 | Z112: 0 | AA112: 0 | AB112: 1023600 | AC112: FINALIZADO | AD112: =+VLOOKUP(T112,items!$A$2:$D$1255,4,0) -> #N/A | AE112: =+VLOOKUP(T112,Tabla1[],5,0) -> #N/A | AF112: =+MONTH(O112) -> 6
A113: 90354 | B113: ATEMPO INVERSIONES S.A.S. | C113: CUBRIMIENTO | D113: 0 | F113: 2024-01-29 | G113: 2024-06-08 | H113: 2024-06-11 13:46:57 | I113: 0000-00-00 00:00:00 | J113: 2024-06-13 07:27:05 | K113: 2024-06-13 07:27:40 | L113: 0000-00-00 00:00:00 | M113: 2024-06-11 | N113: 2024-06-11 | O113: 2024-06-25 | P113: 2024-06-28 | Q113: 2024-06-28 | R113: Aprobado Despachos | S113: Bogota | T113: SERVLAV10 | U113: SERVICIO MTTOLAVADO PERGOLA FIJA | X113: 1 | Y113: 0 | Z113: 0 | AA113: 0 | AB113: 1000000 | AC113: FINALIZADO | AD113: =+VLOOKUP(T113,items!$A$2:$D$1255,4,0) -> #N/A | AE113: =+VLOOKUP(T113,Tabla1[],5,0) -> #N/A | AF113: =+MONTH(O113) -> 6
A114: 90364 | B114: MICHEL CAMILO GALLEGO HENAO | C114: CUBRIMIENTO | D114: 0 | F114: 2024-01-29 | G114: 2024-08-15 | H114: 2024-08-23 09:22:23 | I114: 2024-09-30 16:44:30 | J114: 2024-11-01 08:13:54 | K114: 2024-11-14 08:00:48 | L114: 2024-11-21 20:13:58 | M114: 2024-08-24 | N114: 2024-10-01 | O114: 2024-10-13 | P114: 2024-10-15 | Q114: 2024-10-27 | R114: Aprobado Facturacion | S114: Medellin | T114: FLANCHE01 | U114: FLANCHE NACIONAL GALVANIZADO | W114: Negro Señales - RAL 9004 | X114: 2 | Y114: 4200 | Z114: 0 | AA114: 0 | AB114: 1036964 | AC114: FINALIZADO | AD114: =+VLOOKUP(T114,items!$A$2:$D$1255,4,0) -> 0 | AE114: =+VLOOKUP(T114,Tabla1[],5,0) -> 0 | AF114: =+MONTH(O114) -> 10
...

Sheet Hoja2
A1: pedido | B1: cliente | C1: tipo_producto | D1: oportunidad | E1: razon_anulacion | F1: f_cotizacion | G1: f_pedido | H1: f_comercial | I1: f_diseno | J1: f_produccion | K1: f_despachos | L1: f_instalacion | M1: fe_comercial | N1: fe_diseno | O1: fe_produccion | P1: fe_despachos | Q1: fe_instalacion | R1: estado | S1: regional | T1: id_producto | U1: producto | V1: color | W1: color_estructura | X1: cantidad | Y1: largo | Z1: alto | AA1: proyeccion | AB1: valor_total | AC1: estado_crm | AD1: FAMILIA | AE1: LINEA | AF1: Mes Entrega
A2: 107243 | B2: industrias cattan sa | C2: MUEBLES CC CUBRIMIENTOS | D2: 0 | F2: 2025-08-19 | G2: 2025-08-21 | H2: 2025-08-28 09:37:06 | I2: 2025-10-02 08:01:53 | J2: 0000-00-00 00:00:00 | K2: 0000-00-00 00:00:00 | L2: 0000-00-00 00:00:00 | M2: 2025-08-28 | N2: 2025-10-02 | O2: 2025-11-07 | P2: 2025-11-07 | Q2: 2025-11-07 | R2: Aprobado Diseño | S2: Toscana | T2: PLITE10 | U2: PERGOLITE MAN LON VINI MUROS | V2: PENDIENTE DEFINIR CLIENTE | W2: Gris Antracita - RAL 7016 | X2: 2 | Y2: 6177 | Z2: 0 | AA2: 3553 | AB2: 6743.02 | AC2: PRODUCCION | AD2: PERGOLA | AE2: PERGOLITE | AF2: 11
A3: 107242 | B3: industrias cattan sa | C3: MUEBLES CC CUBRIMIENTOS | D3: 0 | F3: 2025-08-19 | G3: 2025-08-21 | H3: 2025-08-28 09:37:41 | I3: 2025-10-02 08:03:13 | J3: 0000-00-00 00:00:00 | K3: 0000-00-00 00:00:00 | L3: 0000-00-00 00:00:00 | M3: 2025-08-28 | N3: 2025-10-02 | O3: 2025-11-07 | P3: 2025-11-07 | Q3: 2025-11-07 | R3: Aprobado Diseño | S3: Toscana | T3: PLITE10 | U3: PERGOLITE MAN LON VINI MUROS | V3: PENDIENTE DEFINIR CLIENTE | W3: Gris Antracita - RAL 7016 | X3: 2 | Y3: 6367 | Z3: 0 | AA3: 4768 | AB3: 7589.84 | AC3: PRODUCCION | AD3: PERGOLA | AE3: PERGOLITE | AF3: 11
A4: 107070 | B4: DISEÑOS MILANELO SAS | C4: CUBRIMIENTO | D4: 0 | F4: 2025-08-13 | G4: 2025-09-26 | H4: 2025-10-29 16:57:04 | I4: 2025-11-05 18:04:07 | J4: 0000-00-00 00:00:00 | K4: 0000-00-00 00:00:00 | L4: 0000-00-00 00:00:00 | M4: 2025-10-29 | N4: 2025-11-05 | O4: 2025-11-12 | P4: 2025-11-15 | Q4: 2025-11-22 | R4: Aprobado Diseño | S4: Medellin | T4: PLITE10 | U4: PERGOLITE MAN LON VINI MUROS | V4: LONA PERGOTEX BLACKOUT BLANCA 3 M | W4: Negro Señales - RAL 9004 | X4: 5 | Y4: 4500 | Z4: 0 | AA4: 5500 | AB4: 38876835 | AC4: PRODUCCION | AD4: PERGOLA | AE4: PERGOLITE | AF4: 11

Sheet Hoja1
K7: Nota: comunicado a comercial
A16: Suma de cantidad | K16: Suma de cantidad
A17: cliente | B17: pedido | C17: producto | D17: estado | E17: largo | F17: proyeccion | G17: alto | H17: color_estructura | I17: Total | K17: producto | L17: Total
A18: BRENT SCHROEDER | B18: 106801 | C18: SOMBRALINA ELECTRICA | D18: Detenido Diseño | E18: 6000 | F18: 4000 | G18: 0 | H18: Negro Señales - RAL 9004 | I18: 3 | K18: Proyecto Especial | L18: 2
A19: GIOVANA HERNANDEZ | B19: 109111 | C19: SOMBRALINA ELECTRICA | D19: Detenido Comercial | E19: 3176 | F19: 2000 | G19: 0 | H19: Blanco Señal - RAL 9003 | I19: 2 | K19: SOMBRALINA ELECTRICA | L19: 11
A20: GONZALO HERRERA NIETO | B20: 109022 | C20: SOMBRALINA ELECTRICA | D20: Detenido Comercial | E20: 3080 | F20: 2000 | G20: 0 | H20: Blanco Señal - RAL 9003 | I20: 2 | K20: SOMBRALINA ELECTRICA MANUAL | L20: 1
A21: INDUSTRIAS ALIMENTICIAS EL TREBOL S.A.S. | B21: 108506 | C21: Proyecto Especial | D21: Detenido Comercial | E21: 0 | F21: 0 | G21: 0 | H21: (en blanco) | I21: 1 | K21: Total general | L21: 14
E22: 11570 | F22: 9870 | G22: 0 | H22: (en blanco) | I22: 1
A23: INVERSIONES DERANGO S.A.S | B23: 109490 | C23: SOMBRALINA ELECTRICA | D23: Detenido Diseño | E23: 3000 | F23: 2500 | G23: 0 | H23: Marron Tierra - RAL 8028 | I23: 1
A24: Juan Manuel Ospina Montoya | B24: 107726 | C24: SOMBRALINA ELECTRICA | D24: Detenido Comercial | E24: 5150 | F24: 3000 | G24: 0 | H24: Negro Señales - RAL 9004 | I24: 1
A25: M S L DISTRIBUCIONES & CIA S.A.S | B25: 108290 | C25: SOMBRALINA ELECTRICA | D25: En Proceso Diseño | E25: 3640 | F25: 3000 | G25: 0 | H25: Marron Tierra - RAL 8028 | I25: 1
E26: 4700 | F26: 2850 | G26: 0 | H26: Marron Tierra - RAL 8028 | I26: 1
A27: RICARDO DIAZ ROMERO | B27: 109074 | C27: SOMBRALINA ELECTRICA MANUAL | D27: Aprobado Diseño | E27: 10000 | F27: 3740 | G27: 0 | H27: Blanco Perla - RAL 1013 | I27: 1
A28: Total general | I28: 14
A122: Suma de cantidad | B122: estado_crm | C122: estado | R122: Suma de valor_total | S122: estado_crm | T122: estado
B123: COMERCIAL | C123: DISEÑO | E123: PRODUCCION | F123: Total general | S123: COMERCIAL | T123: DISEÑO | V123: PRODUCCION | W123: Total general
A124: producto | B124: Detenido Comercial | C124: Detenido Diseño | D124: En Proceso Diseño | E124: Aprobado Diseño | R124: producto | S124: Detenido Comercial | T124: Detenido Diseño | U124: En Proceso Diseño | V124: Aprobado Diseño
A125: SOMBRALINA ELECTRICA | B125: 5 | C125: 4 | D125: 2 | F125: 11 | R125: Proyecto Especial | S125: 27221976 | W125: 27221976
A126: Proyecto Especial | B126: 2 | F126: 2 | R126: SOMBRALINA ELECTRICA | S126: 27904399 | T126: 36606413 | U126: 14719408 | W126: 79230220
A127: SOMBRALINA ELECTRICA MANUAL | E127: 1 | F127: 1 | R127: SOMBRALINA ELECTRICA MANUAL | V127: 14411175 | W127: 14411175
A128: Total general | B128: 7 | C128: 4 | D128: 2 | E128: 1 | F128: 14 | R128: Total general | S128: 55126375 | T128: 36606413 | U128: 14719408 | V128: 14411175 | W128: 120863371

Sheet Hoja7
A2: riel pergoli | B2: CORTE | C2: ENSAMBLE

Sheet CAPACIDAD PLANTA
D1: centros de trabajo x persona
A2: dias habiles operación | B2: 18 | F2: 19
A3: Horas disponibles Mes | B3: =+B2*8.64 -> 155.52 | C3: =+B3/8.64 -> 18 | F3: =+F2*8.64 -> 164.16
A4: Minutos disponibles Mes | B4: =+B3*60 -> 9331.2
A5: minutos x turno | B5: 518
B9: producto | C9: Total | F9: Corte | G9: Mecanizado | H9: Pintura ** | I9: Ensamble | J9: Costura | K9: Electromecanica
B10: PERGOLITE MAN LON VINI MUROS | C10: 22 | F10: =+(22*28.8) -> 633.6 | G10: =68.8*22 -> 1513.6 | H10: =(0.113*(518))*C10 -> 1287.748 | I10: =+(41.7*22) -> 917.4 | J10: =+(31.5*22) -> 693
B11: PERGOLITE MAN LON VINI POSTES | C11: 1 | F11: 33.7 | G11: 166.4 | H11: =(0.113*(518))*C11 -> 58.534 | I11: 208.6 | J11: 31.5
B12: PERGOLITE MAN LONA ACRILICA MUROS | C12: 5 | F12: =28.8*C12 -> 144 | G12: =68.8*5 -> 344 | H12: =(0.113*(518))*C12 -> 292.67 | I12: =41.7*5 -> 208.5 | J12: =31.5*5 -> 157.5
B13: PLITE MAN LON ACRIL POSTES | C13: 1 | F13: 40.8 | G13: 152.1 | H13: =(0.113*(518))*C13 -> 58.534 | I13: 208.5 | J13: 31.5
B14: Total general | C14: 29 | E14: Total (min) | F14: =SUM(F10:F13) -> 852.1 | G14: =SUM(G10:G13) -> 2176.1 | H14: =SUM(H10:H13) -> 1697.486 | I14: =SUM(I10:I13) -> 1543 | J14: =SUM(J10:J13) -> 913.5
E15: Total (horas) | F15: =+F14/60 -> 14.201667 | G15: =+G14/60 -> 36.268333 | H15: =+H14/60 -> 28.291433 | I15: =+I14/60 -> 25.716667 | J15: =+J14/60 -> 15.225
B17: producto | C17: Total | F17: Corte | G17: Mecanizado | H17: Pintura ** | I17: Ensamble | J17: Costura | K17: Electromecanica
B18: PERGOTEK ROMANO BASIC GAZEBO | C18: 1 | E18: Total (min) | F18: 155 | G18: 224 | H18: =217*C18 -> 217 | I18: 1131
B19: PERGOTEK ROMANO MAXI GAZEBO | C19: 2 | E19: Total (horas) | F19: =+F18/60 -> 2.5833333 | G19: =+G18/60 -> 3.7333333 | H19: =+H18/60 -> 3.6166667 | I19: =+I18/60 -> 18.85
B20: PERGOTEK ROMANO MINI GAZEBO | C20: 1
B21: PERGOTEK ROMANO MINI MUROS | C21: 3
B22: Total general | C22: 7
B25: producto | C25: Total | F25: Corte | G25: Mecanizado | H25: Pintura ** | I25: Ensamble | J25: Costura | K25: Electromecanica
B26: PERGOTEK BASIC CLASSIC CON POSTES | C26: 1 | E26: Total (min) | F26: 143 | G26: 215 | H26: 217 | I26: 1108
B27: PERGOTEK MEGA CLASSIC MUROS | C27: 2 | E27: Total (horas) | F27: =+F26/60 -> 2.3833333 | G27: =+G26/60 -> 3.5833333 | H27: =+H26/60 -> 3.6166667 | I27: =+I26/60 -> 18.466667
B28: PERGOTEK MINI CLASSIC ENTRE MUROS | C28: 2
B29: PERGOTEK MINI CLASSIC POSTES | C29: 1
B30: Total general | C30: 6
B33: producto | C33: Total | F33: Corte | G33: Mecanizado | H33: Pintura ** | I33: Ensamble | J33: Costura | K33: Electromecanica
B34: MAXI PERGOLAM CON POSTES | C34: 6 | F34: =644*C34 -> 3864 | G34: =203*C34 -> 1218 | H34: =1295*C34 -> 7770 | I34: =1813*C34 -> 10878 | K34: =1984*C34 -> 11904
B35: MAXI PERGOLAM ENTRE MUROS | C35: 6 | F35: =659*C35 -> 3954 | G35: =266.9*C35 -> 1601.4 | H35: =1295*C35 -> 7770 | I35: =1759*C35 -> 10554 | K35: =1984*C35 -> 11904
B36: MAXI PERGOLAM GAZEBO | C36: 2 | F36: =677.8*C36 -> 1355.6 | G36: =232.3*C36 -> 464.6 | H36: =1295*C36 -> 2590 | I36: =1867*C36 -> 3734 | K36: =1984*C36 -> 3968
B37: Total general | C37: 14 | E37: Total (min) | F37: =SUM(F34:F36) -> 9173.6 | G37: =SUM(G34:G36) -> 3284 | H37: =SUM(H34:H36) -> 18130 | I37: =SUM(I34:I36) -> 25166 | J37: =SUM(J34:J36) -> 0 | K37: =SUM(K34:K36) -> 27776
E38: Total (horas) | F38: =+F37/60 -> 152.89333 | G38: =+G37/60 -> 54.733333 | H38: =+H37/60 -> 302.16667 | I38: =+I37/60 -> 419.43333 | J38: =+J37/60 -> 0 | K38: =+K37/60 -> 462.93333
F40: Corte | G40: Mecanizado | H40: Pintura ** | I40: Ensamble | J40: Costura | K40: Electromecanica
C41: Total Horas Necesarias | E41: Total (min) | F41: =+F14+F18+F26+F37 -> 10323.7 | G41: =+G14+G18+G26+G37 -> 5899.1 | H41: =+H14+H18+H26+H37 -> 20261.486 | I41: =+I14+I18+I26+I37 -> 28948 | J41: =+J14+J18+J26+J37 -> 913.5 | K41: =+K14+K18+K26+K37 -> 27776
E42: Total (horas) | F42: =+F41/60 -> 172.06167 | G42: =+G41/60 -> 98.318333 | H42: =+H41/60 -> 337.69143 | I42: =+I41/60 -> 482.46667 | J42: =+J41/60 -> 15.225 | K42: =+K41/60 -> 462.93333
E43: Total (dias) | F43: =+F42/8.64 -> 19.914545 | G43: =+G42/8.64 -> 11.379437 | H43: =+H42/8.64 -> 39.084657 | I43: =+I42/8.64 -> 55.841049 | J43: =+J42/8.64 -> 1.7621528 | K43: =+K42/8.64 -> 53.580247
E44: Operarios | F44: 1 | G44: 1 | H44: 1 | I44: 4 | J44: 5 | K44: 1
E45: Total (min) | F45: =+F41/F44 -> 10323.7 | G45: =+G41/G44 -> 5899.1 | H45: =+H41/H44 -> 20261.486 | I45: =+I41/I44 -> 7237 | J45: =+J41/J44 -> 182.7 | K45: =+K41/K44 -> 27776
E46: Total (horas) | F46: =+F45/60 -> 172.06167 | G46: =+G45/60 -> 98.318333 | H46: =+H45/60 -> 337.69143 | I46: =+I45/60 -> 120.61667 | J46: =+J45/60 -> 3.045 | K46: =+K45/60 -> 462.93333
E47: Total (dias) | F47: =+F46/8.64 -> 19.914545 | G47: =+G46/8.64 -> 11.379437 | H47: =+H46/8.64 -> 39.084657 | I47: =+I46/8.64 -> 13.960262 | J47: =+J46/8.64 -> 0.35243056 | K47: =+K46/8.64 -> 53.580247
F48: 155 | G48: 155 | H48: 155 | I48: 155 | J48: 155 | K48: 155
B49: DICIEMBRE | F49: =+F48-F46 -> -17.061667 | G49: =+G48-G46 -> 56.681667 | H49: =+H48-H46 -> -182.69143 | I49: =+I48-I46 -> 34.383333 | J49: =+J48-J46 -> 151.955 | K49: =+K48-K46 -> -307.93333
B52: producto | C52: Total | F52: Corte | G52: Mecanizado | H52: Pintura ** | I52: Ensamble | J52: Costura | K52: Electromecanica
B53: PERGOLITE MAN LON VINI MUROS | C53: 15 | F53: =+($C$53*28.8) -> 432 | G53: =68.8*15 -> 1032 | H53: =(0.113*(518))*C53 -> 878.01 | I53: =+(41.7*15) -> 625.5 | J53: =+(31.5*15) -> 472.5
B54: Total general | C54: 15 | E54: Total (min) | F54: =+F53 -> 432 | G54: =+G53 -> 1032 | H54: =+H53 -> 878.01 | I54: =+I53 -> 625.5 | J54: =+J53 -> 472.5
E55: Total (horas) | F55: =+F54/60 -> 7.2 | G55: =+G54/60 -> 17.2 | H55: =+H54/60 -> 14.6335 | I55: =+I54/60 -> 10.425 | J55: =+J54/60 -> 7.875
B58: producto | C58: Total | F58: Corte | G58: Mecanizado | H58: Pintura ** | I58: Ensamble | J58: Costura | K58: Electromecanica
B59: MAXI PERGOLAM CON POSTES | C59: 4 | F59: =644*C59 -> 2576 | G59: =203*C59 -> 812 | H59: =1295*C59 -> 5180 | I59: =1813*C59 -> 7252 | K59: =1984*C59 -> 7936
B60: MAXI PERGOLAM ENTRE MUROS | C60: 2 | F60: =659*C60 -> 1318 | G60: =266.9*C60 -> 533.8 | H60: =1295*C60 -> 2590 | I60: =1759*C60 -> 3518 | K60: =1984*C60 -> 3968
B61: MAXI PERGOLAM GAZEBO | C61: 1 | F61: =677.8*C61 -> 677.8 | G61: =232.3*C61 -> 232.3 | H61: =1295*C61 -> 1295 | I61: =1867*C61 -> 1867 | K61: =1984*C61 -> 1984
B62: Total general | C62: 7 | E62: Total (min) | F62: =SUM(F59:F61) -> 4571.8 | G62: =SUM(G59:G61) -> 1578.1 | H62: =SUM(H59:H61) -> 9065 | I62: =SUM(I59:I61) -> 12637 | J62: =SUM(J59:J61) -> 0 | K62: =SUM(K59:K61) -> 13888
E63: Total (horas) | F63: =+F62/60 -> 76.196667 | G63: =+G62/60 -> 26.301667 | H63: =+H62/60 -> 151.08333 | I63: =+I62/60 -> 210.61667 | J63: =+J62/60 -> 0 | K63: =+K62/60 -> 231.46667
B66: producto | C66: Total
B67: PFAT08 PERGOLA FIJA ACERO TECA PEQUEÃ?A | C67: 6
B68: Total general | C68: 6
B71: producto | C71: Total | F71: Corte | G71: Mecanizado | H71: Pintura ** | I71: Ensamble | J71: Costura | K71: Electromecanica
B72: PERGOTEK ROMANO BASIC MUROS | C72: 1 | F72: 145 | G72: 167 | H72: =+(0.4*518) -> 207.2 | I72: 1251 | K72: 313
B73: PERGOTEK ROMANO MAXI POSTES | C73: 2
B74: PERGOTEK ROMANO MEGA MUROS | C74: 3
B75: Total general | C75: 6 | E75: Total (min) | F75: =+F72 -> 145 | G75: =+G72 -> 167 | H75: =+H72 -> 207.2 | I75: =+I72 -> 1251 | J75: =+J72 -> 0 | K75: =+K72 -> 313
E76: Total (horas) | F76: =+F75/60 -> 2.4166667 | G76: =+G75/60 -> 2.7833333 | H76: =+H75/60 -> 3.4533333 | I76: =+I75/60 -> 20.85 | J76: =+J75/60 -> 0 | K76: =+K75/60 -> 5.2166667
D81: DICIEMBRE | F81: Corte | G81: Mecanizado | H81: Pintura ** | I81: Ensamble | J81: Costura | K81: Electromecanica
E82: Total (min) | F82: =+F54+F62+F75+F78 -> 5148.8 | G82: =+G54+G62+G75+G78 -> 2777.1 | H82: =+H54+H62+H75+H78 -> 10150.21 | I82: =+I54+I62+I75+I78 -> 14513.5 | J82: =+J54+J62+J75+J78 -> 472.5 | K82: =+K54+K62+K75+K78 -> 14201
E83: Total (horas) | F83: =+F82/60 -> 85.813333 | G83: =+G82/60 -> 46.285 | H83: =+H82/60 -> 169.17017 | I83: =+I82/60 -> 241.89167 | J83: =+J82/60 -> 7.875 | K83: =+K82/60 -> 236.68333
E84: Total (dias) | F84: =+F83/8.64 -> 9.9320988 | G84: =+G83/8.64 -> 5.3570602 | H84: =+H83/8.64 -> 19.57988 | I84: =+I83/8.64 -> 27.996721 | J84: =+J83/8.64 -> 0.91145833 | K84: =+K83/8.64 -> 27.393904
E85: Operarios | F85: 1 | G85: 1 | H85: 1 | I85: 4 | J85: 5 | K85: 1
E86: Total (min) | F86: =+F82/F85 -> 5148.8 | G86: =+G82/G85 -> 2777.1 | H86: =+H82/H85 -> 10150.21 | I86: =+I82/I85 -> 3628.375 | J86: =+J82/J85 -> 94.5 | K86: =+K82/K85 -> 14201
E87: Total (horas) | F87: =+F86/60 -> 85.813333 | G87: =+G86/60 -> 46.285 | H87: =+H86/60 -> 169.17017 | I87: =+I86/60 -> 60.472917 | J87: =+J86/60 -> 1.575 | K87: =+K86/60 -> 236.68333
E88: Total (dias) | F88: =+F87/8.64 -> 9.9320988 | G88: =+G87/8.64 -> 5.3570602 | H88: =+H87/8.64 -> 19.57988 | I88: =+I87/8.64 -> 6.9991802 | J88: =+J87/8.64 -> 0.18229167 | K88: =+K87/8.64 -> 27.393904
F89: 164 | G89: 164 | H89: 164 | I89: 164 | J89: 164 | K89: 164
F90: =+F89-F87 -> 78.186667 | G90: =+G89-G87 -> 117.715 | H90: =+H89-H87 -> -5.1701667 | I90: =+I89-I87 -> 103.52708 | J90: =+J89-J87 -> 162.425 | K90: =+K89-K87 -> -72.683333
E91: general
G93: Corte | H93: Pintura ** | I93: Mecanizado-Ensamble | J93: Costura | K93: Electromecanica
F94: Total (min) | G94: =+F41+F82 -> 15472.5 | H94: =+H41+H82 -> 30411.696 | I94: 52137.7 | J94: =+J41+J82 -> 1386 | K94: =+K41+K82 -> 41977
F95: Total (horas) | G95: =+G94/60 -> 257.875 | H95: =+H94/60 -> 506.8616 | I95: =+I94/60 -> 868.96167 | J95: =+J94/60 -> 23.1 | K95: =+K94/60 -> 699.61667
F96: Total (dias) | G96: =+G95/8.64 -> 29.846644 | H96: =+H95/8.64 -> 58.664537 | I96: =+I95/8.64 -> 100.57427 | J96: =+J95/8.64 -> 2.6736111 | K96: =+K95/8.64 -> 80.974151
F97: Operarios | G97: 1 | H97: 1 | I97: 2 | J97: 5 | K97: 1
F98: Total (min) | G98: =+G94 -> 15472.5 | H98: =+H94/H97 -> 30411.696 | I98: =+I94/I97 -> 26068.85 | J98: =+J94/J97 -> 277.2 | K98: =+K94/K97 -> 41977
F99: Total (horas) | G99: =+G98/60 -> 257.875 | H99: =+H98/60 -> 506.8616 | I99: =+I98/60 -> 434.48083 | J99: =+J98/60 -> 4.62 | K99: =+K98/60 -> 699.61667
F100: Total (dias) | G100: =+G99/8.64 -> 29.846644 | H100: =+H99/8.64 -> 58.664537 | I100: =+I99/8.64 -> 50.287133 | J100: =+J99/8.64 -> 0.53472222 | K100: =+K99/8.64 -> 80.974151
F101: Total (dias-habiles) | G101: 36.5 | H101: 36.5 | I101: 36.5 | J101: 36.5 | K101: 36.5
G102: 319 | H102: 319 | I102: 319 | J102: 319 | K102: 319
G103: =+G102-G99 -> 61.125 | H103: =+H102-H99 -> -187.8616 | I103: =+I102-I99 -> -115.48083 | J103: =+J102-J99 -> 314.38 | K103: =+K102-K99 -> -380.61667

Sheet items
A1: id_producto | B1: producto | C1: CLASIFICACION | D1: FAMILIA | E1: LINEA
A2: 98731 | B2: ACOPLE DESPL. SUP. MASTIL. SOMBR. ROMA.
A3: REP045 | B3: REPARACION SOMBRILLA MANO OBRA
A4: 15477 | B4: MESA DE CENTRO JAPON ALUTECA 1*1(TA) | C4: PRODUCTO TERMINADO | D4: MUEBLES
A5: 15479 | B5: SOFA JAPON ALUTECA TRES PUESTOS C/C | C5: PRODUCTO TERMINADO | D5: MUEBLES
A6: 15481 | B6: POLTRONA JAPON ALUTECA C/C | C6: PRODUCTO TERMINADO | D6: MUEBLES
A7: 19353 | B7: PASADOR PUERTA CONICO P/FLEXIGLASS
A8: FGLASS01 | B8: FLEXIGLASS 10 mm | C8: PRODUCTO TERMINADO | D8: FLEXIGLASS
A9: 2043 | B9: MESA BISTRO 0.70*0.70 C/BM (TL) | C9: PRODUCTO TERMINADO | D9: MUEBLES
A10: PFAT07 | B10: PERGOLA FIJA ACEROTECA GRANDE | C10: PRODUCTO TERMINADO | D10: PERGOLA | E10: PERGOLA FIJA
A11: PLAM05 | B11: MAXI PERGOLAM CON POSTES | C11: PRODUCTO TERMINADO | D11: PERGOLA | E11: MAXI PERGOLAM
A12: 18013 | B12: TORN PRIS 8mmX8 DIAM P/FLEXIGLASS PLUS
A13: 18447 | B13: FG+STACION SUPERIOR PUERTA (DAP1720)
A14: 18448 | B14: FG+ESTACION INFERIOR PUERTA (DAP1721)
A15: 18451 | B15: FG+TAPA IZQUIERDA BLANCA (DAP1724)
A16: 18452 | B16: FG+TAPA DERECHA BLANCA (DAP1725)
A17: 18453 | B17: FG+CUADRANTE (DAP1726)
A18: 18455 | B18: FG+ESTACION SUPERIOR (DAP1709)
A19: 18456 | B19: RETENEDOR ESTACIONAM INF PUERTA(DAP1705)
A20: 18457 | B20: FG+BUJE SUPERIOR (DAP1728)
A21: 18458 | B21: FG+BUJE INFERIOR (DAP1729)
A22: 19544 | B22: FG+BISAGRA PUERTA ZAMAK
A23: 19545 | B23: FG+BISAGRA SUPERIOR ZAMAK
... A37: 6277 | B37: LONA PERGOTEX BLACKOUT BLANCA 3 M
A38: 6752 | B38: FUNDA SOMBRILLA ROMA 3.0 X 3.0M | C38: PRODUCTO TERMINADO | D38: FUNDA
A39: PTEKROM12 | B39: PERGOTEK ROMANO MINI MUROS | C39: PRODUCTO TERMINADO | D39: PERGOLA | E39: PERGOTEK ROMANO
A40: 180331 | B40: CINTA ALUMINIO 25mmX33mts
A41: 25769 | B41: SELLADOR ADHESIVO PU 50 BLANCO 600 ML SA
A42: REP035 | B42: REPARACION PERGOLA MAT PRIMA
A43: 13672 | B43: ASOLEADORA VICHADA (TA) | C43: PRODUCTO TERMINADO | D43: MUEBLES
A44: TRANSP07 | B44: TRANSPORTE FUERA DE CALI MUEBLES
A45: REP029 | B45: REPARACION MEMBRANA MANO OBRA
A46: REP030 | B46: REPARACION MEMBRANA MAT PRIMA
A47: FLANCHE01 | B47: FLANCHE NACIONAL GALVANIZADO
A48: PLT45 | B48: PLATINA ANCLAJE POSTEMURO PERF.127x127
A49: PTEKROM02 | B49: PERGOTEK ROMANO MEGA MUROS | C49: PRODUCTO TERMINADO | D49: PERGOLA | E49: PERGOTEK ROMANO
A50: SPOT30 | B50: SISTEMA ELECTRICO 30 SPOT PARA PERGOLA
A51: PLAM08 | B51: MAXI PERGOLAM GAZEBO | C51: PRODUCTO TERMINADO | D51: PERGOLA | E51: MAXI PERGOLAM
A52: 9683 | B52: MALLA SILLA VENUS
A53: 3151 | B53: CORREA DENTADA 19mm PERGOLAS RETRACTILES
A54: REP007 | B54: REPARACION BANETA GUILLO MAT PRIMA
A55: 27313 | B55: CAJA GUAYA 100KG CHINA
A56: REP027 | B56: REPARACION LONA MAT PRIMA
A57: 22752 | B57: SIKAFLEX 545 BLANCA
A58: 27249 | B58: ANCLAJE EPOX CA1400 SOUDAL 280ML
A59: CANAL GALVANIZ PTEK | B59: CANAL GALVANIZADA PERGOTEK
A60: CUBT03 | B60: CUBIERTA EN POLICARBONATO
A61: PFLT05 | B61: PERGOLA FIJA ALUTECA GRANDE | C61: PRODUCTO TERMINADO | D61: PERGOLA | E61: PERGOLA FIJA
A62: PTAC03 | B62: POSTE ACERO 120x120
A63: SOLAPA01 | B63: PERFIL SOLAPA
A64: SPOT26 | B64: SISTEMA ELECTRICO 26 SPOT PARA PERGOLA
A65: SOMB01 | B65: SOMBRALINA ELECTRICA | C65: PRODUCTO TERMINADO | D65: SOMBRALINA | E65: ELECTRICA
A66: REP036 | B66: REPARACION PERGOLA MANO OBRA
A67: PLT08 | B67: SOPORTE A PARED PERGOTEK MINI
A68: SPOT10 | B68: SISTEMA ELECTRICO 10 SPOT PARA PERGOLA
A69: CUBT02 | B69: CUBIERTA LONA PVC
A70: PTEKROM21 | B70: PERGOTEK ROMANO BASIC MUROS | C70: PRODUCTO TERMINADO | D70: PERGOLA | E70: PERGOTEK ROMANO
A71: SPOT22 | B71: SISTEMA ELECTRICO 22 SPOT PARA PERGOLA
A72: 100231 | B72: POLTRONA MONTECARLO C/COJIN. (TA) | C72: PRODUCTO TERMINADO | D72: MUEBLES
A73: 100233 | B73: SOFA MONTECARLO 3 PUESTOS C/COJIN. (TA) | C73: PRODUCTO TERMINADO | D73: MUEBLES
A74: 100260 | B74: ASOLEADORA NORMANDIA C/COJIN. (TA) | C74: PRODUCTO TERMINADO | D74: MUEBLES
A75: 110122 | B75: MESA DE CENTRO MONTEC TBLI 120x120 (TA) | C75: PRODUCTO TERMINADO | D75: MUEBLES
A76: 14784 | B76: SILLA APILABLE BRETANA C/BRAZO (TA) | C76: PRODUCTO TERMINADO | D76: MUEBLES
A77: 14785 | B77: SILLA APILABLE SENCILLA BRETAÃ?A (TA) | C77: PRODUCTO TERMINADO | D77: MUEBLES
A78: 15537 | B78: SOMBRILLA ALSACIA 3.5*3.5 MADERA (T) | C78: PRODUCTO TERMINADO
A79: 15841 | B79: SILLA BAR MADERA BRETAÃ?A (TA) | C79: PRODUCTO TERMINADO | D79: MUEBLES
A80: 27646 | B80: MESA ALPES DESAR 1.40*1.40(TA) | C80: PRODUCTO TERMINADO | D80: MUEBLES
A81: 27647 | B81: MESA EXT ALPES DESAR 110X240 EXT 120(TA) | C81: PRODUCTO TERMINADO | D81: MUEBLES
A82: 27649 | B82: MESA BAR MONTECARLO DESAR 1.80*100 (TA) | C82: PRODUCTO TERMINADO | D82: MUEBLES
A83: 5326 | B83: BASE METAL SOMBRILLA 600*600 EN 3/16"M58
A84: 9511 | B84: MESA AUXILIAR MONTECA 60*60 T/ABL (TA) | C84: PRODUCTO TERMINADO | D84: MUEBLES
A85: 9561 | B85: BAR MONTECARLO (TA) | C85: PRODUCTO TERMINADO | D85: MUEBLES
A86: 9591 | B86: CARRO BAR BRETAÃ?A (TA) | C86: PRODUCTO TERMINADO | D86: MUEBLES
A87: 9678 | B87: MESA CIRCULAR ALPES 1.60 (TA) | C87: PRODUCTO TERMINADO | D87: MUEBLES
A88: 9712 | B88: SOMBRILLA ALPES 3.0*3.0 S/F 8P (TA) | C88: PRODUCTO TERMINADO
A89: 9715 | B89: SOMBRILLA ALPES 3.00 8P (TA) | C89: PRODUCTO TERMINADO
A90: FLANCHE02 | B90: FLANCHE SOMBRALINA ALUMINIO
A91: PLT01 | B91: SOPORTE ESP FIJACION SOMBRALINA 130X64
A92: PLITE14 | B92: PERGOLITE MAN LONA ACRILICA MUROS | C92: PRODUCTO TERMINADO | D92: PERGOLA | E92: PERGOLITE
A93: PLT09 | B93: SOPORTE EXTENSION PERGOTEK MINI
A94: TRANSP01 | B94: TRANSPORTE FUERA DE CALI CUBRIMIENTOS
A95: 101747 | B95: TORN AVELLAN BRISTOL MM 6*16 INOX 304
A96: 101829 | B96: EMPAQUE SILICONA CARRO DOBLE PERGOTEK
A97: 18644 | B97: SOLAPA ANTILLUVIA PERGOTEK BASIC 4.0MTS
A98: 24853 | B98: CONTROL REMOTO DOMOTICA DC1662E 15 CHANE
A99: 3688 | B99: SUJETADOR CORREA 20MM
A100: 3713 | B100: SUJETADOR CORREA 20MM COMPLEMENTO
A101: 3724 | B101: TAPA HUECO RIEL BASIC INFERIOR
A102: 3729 | B102: TAPA HUECO RIEL BASIC SUPERIOR
A103: 12714 | B103: EST SOMBRILLA LA GREAT 6.0 S/F | C103: PRODUCTO TERMINADO
A104: 12741 | B104: LONA SOMBRILLA LA GREAT 6.00 MT S/F
A105: 101983 | B105: CONTROL REMOTO DC1702 15 CANALES
A106: 26961 | B106: SIKASIL IA 300 ML NEGRO
A107: 10066 | B107: BASE METALI SOMBRILLA 400*400 EN 5/8"M38
A108: 8829 | B108: SOMBRILLA ALPES 2.0*2.0 4P TECALUM S/F | C108: PRODUCTO TERMINADO
A109: PUBL01 | B109: PUBLICIDAD MONOCROMATICA 1 TINTA
A110: 27832 | B110: BASE METALI SOMBRILLA 250*250 EN 3/8
A111: 9719 | B111: SOMBRILLA ALPES 4.0 8P (TA) | C111: PRODUCTO TERMINADO
A112: 12473 | B112: ANCLAJE EPOXICO HY MM
A113: 15692 | B113: PERFIL ALUM T 007 ANODI 2" x 11/2 CL1003
...
